{
"type": "FeatureCollection",
"name": "map-points",
"crs": { "type": "name", "properties": { "name": "urn:ogc:def:crs:OGC:1.3:CRS84" } },
"features": [
{ "type": "Feature", "properties": { "osm_id": "256710308", "name": "ほﾉ門", "barrier": "gate", "highway": null, "ref": null, "address": null, "is_in": null, "place": null, "man_made": null, "other_tags": null, "area": null, "centroid_x": 134.6936215, "centroid_y": 34.839677 }, "geometry": { "type": "Point", "coordinates": [ 134.6936215, 34.839677 ] } },
{ "type": "Feature", "properties": { "osm_id": "309451090", "name": "るの門", "barrier": "gate", "highway": null, "ref": null, "address": null, "is_in": null, "place": null, "man_made": null, "other_tags": null, "area": null, "centroid_x": 134.6932457, "centroid_y": 34.8387332 }, "geometry": { "type": "Point", "coordinates": [ 134.6932457, 34.8387332 ] } },
{ "type": "Feature", "properties": { "osm_id": "2094415280", "name": "お菊井", "barrier": null, "highway": null, "ref": null, "address": null, "is_in": null, "place": null, "man_made": "water_well", "other_tags": "\"name:en\"=>\"Okiku Well\",\"name:ja\"=>\"お菊井\"", "area": null, "centroid_x": 134.6938146, "centroid_y": 34.8385927 }, "geometry": { "type": "Point", "coordinates": [ 134.6938146, 34.8385927 ] } },
{ "type": "Feature", "properties": { "osm_id": "2449077911", "name": "本町", "barrier": null, "highway": null, "ref": null, "address": null, "is_in": null, "place": "quarter", "man_made": null, "other_tags": "\"name:en\"=>\"Honmachi\",\"name:ja\"=>\"本町\",\"name:ja-Hira\"=>\"ほんまち\"", "area": null, "centroid_x": 134.694037, "centroid_y": 34.8380847 }, "geometry": { "type": "Point", "coordinates": [ 134.694037, 34.8380847 ] } },
{ "type": "Feature", "properties": { "osm_id": "2483146475", "name": "世界遺産 姫路城", "barrier": null, "highway": null, "ref": null, "address": null, "is_in": null, "place": null, "man_made": null, "other_tags": "\"historic\"=>\"memorial\",\"memorial\"=>\"stone\"", "area": null, "centroid_x": 134.6934692, "centroid_y": 34.8363637 }, "geometry": { "type": "Point", "coordinates": [ 134.69346920000001, 34.8363637 ] } },
{ "type": "Feature", "properties": { "osm_id": "2483146481", "name": null, "barrier": null, "highway": null, "ref": null, "address": null, "is_in": null, "place": null, "man_made": null, "other_tags": "\"amenity\"=>\"bench\"", "area": null, "centroid_x": 134.693759, "centroid_y": 34.836456 }, "geometry": { "type": "Point", "coordinates": [ 134.693759, 34.836456 ] } },
{ "type": "Feature", "properties": { "osm_id": "2483148633", "name": "武蔵野御殿跡", "barrier": null, "highway": null, "ref": null, "address": null, "is_in": null, "place": null, "man_made": null, "other_tags": "\"historic\"=>\"archaeological_site\"", "area": null, "centroid_x": 134.6926423, "centroid_y": 34.8365125 }, "geometry": { "type": "Point", "coordinates": [ 134.692642299999989, 34.8365125 ] } },
{ "type": "Feature", "properties": { "osm_id": "2483149323", "name": "千姫ぼたん園石碑", "barrier": null, "highway": null, "ref": null, "address": null, "is_in": null, "place": null, "man_made": null, "other_tags": "\"historic\"=>\"monument\"", "area": null, "centroid_x": 134.6922047, "centroid_y": 34.8367828 }, "geometry": { "type": "Point", "coordinates": [ 134.6922047, 34.8367828 ] } },
{ "type": "Feature", "properties": { "osm_id": "2483149351", "name": null, "barrier": null, "highway": null, "ref": null, "address": null, "is_in": null, "place": null, "man_made": null, "other_tags": "\"amenity\"=>\"vending_machine\",\"check_date\"=>\"2023-10-01\"", "area": null, "centroid_x": 134.6925189, "centroid_y": 34.8375196 }, "geometry": { "type": "Point", "coordinates": [ 134.69251890000001, 34.8375196 ] } },
{ "type": "Feature", "properties": { "osm_id": "2483149646", "name": "公園中心のモニュメント", "barrier": null, "highway": null, "ref": null, "address": null, "is_in": null, "place": null, "man_made": null, "other_tags": "\"historic\"=>\"monument\"", "area": null, "centroid_x": 134.6915757, "centroid_y": 34.8370828 }, "geometry": { "type": "Point", "coordinates": [ 134.691575699999987, 34.8370828 ] } },
{ "type": "Feature", "properties": { "osm_id": "2483150309", "name": "歩兵第十連隊後碑", "barrier": null, "highway": null, "ref": null, "address": null, "is_in": null, "place": null, "man_made": null, "other_tags": "\"historic\"=>\"memorial\"", "area": null, "centroid_x": 134.693859, "centroid_y": 34.837921 }, "geometry": { "type": "Point", "coordinates": [ 134.693859, 34.837921 ] } },
{ "type": "Feature", "properties": { "osm_id": "2483151052", "name": "下山里展望台開設記念碑", "barrier": null, "highway": null, "ref": null, "address": null, "is_in": null, "place": null, "man_made": null, "other_tags": "\"historic\"=>\"memorial\"", "area": null, "centroid_x": 134.6937261, "centroid_y": 34.837973 }, "geometry": { "type": "Point", "coordinates": [ 134.6937261, 34.837973 ] } },
{ "type": "Feature", "properties": { "osm_id": "2483152078", "name": "喫煙所", "barrier": null, "highway": null, "ref": null, "address": null, "is_in": null, "place": null, "man_made": null, "other_tags": "\"smoking:outside\"=>\"yes\"", "area": null, "centroid_x": 134.6928067, "centroid_y": 34.8380953 }, "geometry": { "type": "Point", "coordinates": [ 134.6928067, 34.8380953 ] } },
{ "type": "Feature", "properties": { "osm_id": "2483152079", "name": "鷺庵", "barrier": null, "highway": null, "ref": null, "address": null, "is_in": null, "place": null, "man_made": null, "other_tags": "\"historic\"=>\"monument\"", "area": null, "centroid_x": 134.6919366, "centroid_y": 34.8378493 }, "geometry": { "type": "Point", "coordinates": [ 134.6919366, 34.8378493 ] } },
{ "type": "Feature", "properties": { "osm_id": "2483153738", "name": "迎賓館側 石灯籠", "barrier": null, "highway": null, "ref": null, "address": null, "is_in": null, "place": null, "man_made": null, "other_tags": "\"historic\"=>\"archaeological_site\"", "area": null, "centroid_x": 134.6923475, "centroid_y": 34.8379672 }, "geometry": { "type": "Point", "coordinates": [ 134.692347500000011, 34.8379672 ] } },
{ "type": "Feature", "properties": { "osm_id": "2483154559", "name": "井戸", "barrier": null, "highway": null, "ref": null, "address": null, "is_in": null, "place": null, "man_made": "water_well", "other_tags": null, "area": null, "centroid_x": 134.6933765, "centroid_y": 34.8382858 }, "geometry": { "type": "Point", "coordinates": [ 134.6933765, 34.8382858 ] } },
{ "type": "Feature", "properties": { "osm_id": "2483156653", "name": "下山里", "barrier": null, "highway": null, "ref": null, "address": null, "is_in": null, "place": null, "man_made": null, "other_tags": "\"historic\"=>\"archaeological_site\"", "area": null, "centroid_x": 134.6938001, "centroid_y": 34.8381884 }, "geometry": { "type": "Point", "coordinates": [ 134.6938001, 34.8381884 ] } },
{ "type": "Feature", "properties": { "osm_id": "2483157001", "name": "上山里", "barrier": null, "highway": null, "ref": null, "address": null, "is_in": null, "place": null, "man_made": null, "other_tags": "\"tourism\"=>\"viewpoint\"", "area": null, "centroid_x": 134.6938089, "centroid_y": 34.8383986 }, "geometry": { "type": "Point", "coordinates": [ 134.6938089, 34.8383986 ] } },
{ "type": "Feature", "properties": { "osm_id": "2483253200", "name": "石灯籠", "barrier": null, "highway": null, "ref": null, "address": null, "is_in": null, "place": null, "man_made": null, "other_tags": "\"historic\"=>\"archaeological_site\"", "area": null, "centroid_x": 134.6931161, "centroid_y": 34.8384826 }, "geometry": { "type": "Point", "coordinates": [ 134.6931161, 34.8384826 ] } },
{ "type": "Feature", "properties": { "osm_id": "2483255220", "name": null, "barrier": "gate", "highway": null, "ref": null, "address": null, "is_in": null, "place": null, "man_made": null, "other_tags": "\"bicycle\"=>\"no\",\"foot\"=>\"no\"", "area": null, "centroid_x": 134.6927299, "centroid_y": 34.8384976 }, "geometry": { "type": "Point", "coordinates": [ 134.692729899999989, 34.8384976 ] } },
{ "type": "Feature", "properties": { "osm_id": "2483258333", "name": null, "barrier": null, "highway": null, "ref": null, "address": null, "is_in": null, "place": null, "man_made": null, "other_tags": "\"amenity\"=>\"bench\",\"backrest\"=>\"no\",\"material\"=>\"stone\",\"seats\"=>\"3\"", "area": null, "centroid_x": 134.6921622, "centroid_y": 34.8365021 }, "geometry": { "type": "Point", "coordinates": [ 134.692162200000013, 34.8365021 ] } },
{ "type": "Feature", "properties": { "osm_id": "2483258334", "name": null, "barrier": null, "highway": null, "ref": null, "address": null, "is_in": null, "place": null, "man_made": null, "other_tags": "\"amenity\"=>\"bench\",\"backrest\"=>\"no\",\"material\"=>\"stone\",\"seats\"=>\"3\"", "area": null, "centroid_x": 134.6920949, "centroid_y": 34.8365621 }, "geometry": { "type": "Point", "coordinates": [ 134.6920949, 34.8365621 ] } },
{ "type": "Feature", "properties": { "osm_id": "2483258335", "name": null, "barrier": null, "highway": null, "ref": null, "address": null, "is_in": null, "place": null, "man_made": null, "other_tags": "\"amenity\"=>\"bench\",\"backrest\"=>\"no\",\"material\"=>\"stone\",\"seats\"=>\"3\"", "area": null, "centroid_x": 134.6918619, "centroid_y": 34.8367341 }, "geometry": { "type": "Point", "coordinates": [ 134.6918619, 34.8367341 ] } },
{ "type": "Feature", "properties": { "osm_id": "2483258336", "name": null, "barrier": null, "highway": null, "ref": null, "address": null, "is_in": null, "place": null, "man_made": null, "other_tags": "\"amenity\"=>\"bench\",\"backrest\"=>\"no\",\"material\"=>\"stone\",\"seats\"=>\"3\"", "area": null, "centroid_x": 134.6918089, "centroid_y": 34.8367529 }, "geometry": { "type": "Point", "coordinates": [ 134.691808900000012, 34.8367529 ] } },
{ "type": "Feature", "properties": { "osm_id": "2483258337", "name": null, "barrier": null, "highway": null, "ref": null, "address": null, "is_in": null, "place": null, "man_made": null, "other_tags": "\"amenity\"=>\"bench\",\"backrest\"=>\"no\",\"material\"=>\"stone\",\"seats\"=>\"3\"", "area": null, "centroid_x": 134.6914441, "centroid_y": 34.8367528 }, "geometry": { "type": "Point", "coordinates": [ 134.691444100000012, 34.8367528 ] } },
{ "type": "Feature", "properties": { "osm_id": "2483258338", "name": null, "barrier": null, "highway": null, "ref": null, "address": null, "is_in": null, "place": null, "man_made": null, "other_tags": "\"amenity\"=>\"bench\",\"backrest\"=>\"no\",\"material\"=>\"stone\",\"seats\"=>\"3\"", "area": null, "centroid_x": 134.6913101, "centroid_y": 34.8368056 }, "geometry": { "type": "Point", "coordinates": [ 134.69131010000001, 34.8368056 ] } },
{ "type": "Feature", "properties": { "osm_id": "2483258339", "name": null, "barrier": null, "highway": null, "ref": null, "address": null, "is_in": null, "place": null, "man_made": null, "other_tags": "\"amenity\"=>\"bench\",\"backrest\"=>\"no\",\"material\"=>\"stone\",\"seats\"=>\"3\"", "area": null, "centroid_x": 134.6911768, "centroid_y": 34.8368481 }, "geometry": { "type": "Point", "coordinates": [ 134.6911768, 34.8368481 ] } },
{ "type": "Feature", "properties": { "osm_id": "2483258340", "name": null, "barrier": null, "highway": null, "ref": null, "address": null, "is_in": null, "place": null, "man_made": null, "other_tags": "\"amenity\"=>\"bench\",\"backrest\"=>\"no\",\"bench\"=>\"yes\",\"material\"=>\"stone\",\"seats\"=>\"2\"", "area": null, "centroid_x": 134.6911025, "centroid_y": 34.8370529 }, "geometry": { "type": "Point", "coordinates": [ 134.6911025, 34.8370529 ] } },
{ "type": "Feature", "properties": { "osm_id": "2483258341", "name": null, "barrier": null, "highway": null, "ref": null, "address": null, "is_in": null, "place": null, "man_made": null, "other_tags": "\"amenity\"=>\"bench\",\"backrest\"=>\"no\",\"material\"=>\"stone\",\"seats\"=>\"2\"", "area": null, "centroid_x": 134.6911115, "centroid_y": 34.8371158 }, "geometry": { "type": "Point", "coordinates": [ 134.6911115, 34.8371158 ] } },
{ "type": "Feature", "properties": { "osm_id": "2483258342", "name": null, "barrier": null, "highway": null, "ref": null, "address": null, "is_in": null, "place": null, "man_made": null, "other_tags": "\"amenity\"=>\"bench\",\"backrest\"=>\"no\",\"material\"=>\"stone\",\"seats\"=>\"2\"", "area": null, "centroid_x": 134.6911176, "centroid_y": 34.8371701 }, "geometry": { "type": "Point", "coordinates": [ 134.691117600000013, 34.8371701 ] } },
{ "type": "Feature", "properties": { "osm_id": "2483261146", "name": null, "barrier": null, "highway": null, "ref": null, "address": null, "is_in": null, "place": null, "man_made": null, "other_tags": "\"amenity\"=>\"bench\",\"backrest\"=>\"no\"", "area": null, "centroid_x": 134.6924898, "centroid_y": 34.836874 }, "geometry": { "type": "Point", "coordinates": [ 134.6924898, 34.836874 ] } },
{ "type": "Feature", "properties": { "osm_id": "2483261147", "name": null, "barrier": null, "highway": null, "ref": null, "address": null, "is_in": null, "place": null, "man_made": null, "other_tags": "\"amenity\"=>\"bench\",\"backrest\"=>\"no\"", "area": null, "centroid_x": 134.6924913, "centroid_y": 34.8369194 }, "geometry": { "type": "Point", "coordinates": [ 134.6924913, 34.8369194 ] } },
{ "type": "Feature", "properties": { "osm_id": "2483261148", "name": null, "barrier": null, "highway": null, "ref": null, "address": null, "is_in": null, "place": null, "man_made": null, "other_tags": "\"amenity\"=>\"bench\",\"backrest\"=>\"no\"", "area": null, "centroid_x": 134.6924923, "centroid_y": 34.8369521 }, "geometry": { "type": "Point", "coordinates": [ 134.6924923, 34.8369521 ] } },
{ "type": "Feature", "properties": { "osm_id": "2483261149", "name": null, "barrier": null, "highway": null, "ref": null, "address": null, "is_in": null, "place": null, "man_made": null, "other_tags": "\"amenity\"=>\"bench\",\"backrest\"=>\"no\"", "area": null, "centroid_x": 134.6924935, "centroid_y": 34.8369909 }, "geometry": { "type": "Point", "coordinates": [ 134.692493500000012, 34.8369909 ] } },
{ "type": "Feature", "properties": { "osm_id": "2483261416", "name": null, "barrier": null, "highway": null, "ref": null, "address": null, "is_in": null, "place": null, "man_made": null, "other_tags": "\"amenity\"=>\"bench\",\"backrest\"=>\"no\",\"colour\"=>\"gray\",\"material\"=>\"stone\",\"seats\"=>\"2\"", "area": null, "centroid_x": 134.6911385, "centroid_y": 34.8373532 }, "geometry": { "type": "Point", "coordinates": [ 134.6911385, 34.8373532 ] } },
{ "type": "Feature", "properties": { "osm_id": "2483261421", "name": null, "barrier": null, "highway": null, "ref": null, "address": null, "is_in": null, "place": null, "man_made": null, "other_tags": "\"amenity\"=>\"bench\",\"backrest\"=>\"no\",\"colour\"=>\"gray\",\"material\"=>\"stone\",\"seats\"=>\"2\"", "area": null, "centroid_x": 134.6911587, "centroid_y": 34.8374581 }, "geometry": { "type": "Point", "coordinates": [ 134.691158699999988, 34.8374581 ] } },
{ "type": "Feature", "properties": { "osm_id": "2483261426", "name": null, "barrier": null, "highway": null, "ref": null, "address": null, "is_in": null, "place": null, "man_made": null, "other_tags": "\"amenity\"=>\"bench\",\"backrest\"=>\"no\",\"colour\"=>\"gray\",\"material\"=>\"stone\",\"seats\"=>\"2\"", "area": null, "centroid_x": 134.6911626, "centroid_y": 34.8375369 }, "geometry": { "type": "Point", "coordinates": [ 134.691162600000013, 34.8375369 ] } },
{ "type": "Feature", "properties": { "osm_id": "2483278003", "name": null, "barrier": null, "highway": null, "ref": null, "address": null, "is_in": null, "place": null, "man_made": null, "other_tags": "\"amenity\"=>\"bench\",\"backrest\"=>\"no\",\"material\"=>\"stone\",\"seats\"=>\"2\"", "area": null, "centroid_x": 134.691537, "centroid_y": 34.8377353 }, "geometry": { "type": "Point", "coordinates": [ 134.691537, 34.8377353 ] } },
{ "type": "Feature", "properties": { "osm_id": "2483278004", "name": null, "barrier": null, "highway": null, "ref": null, "address": null, "is_in": null, "place": null, "man_made": null, "other_tags": "\"amenity\"=>\"bench\",\"backrest\"=>\"no\",\"material\"=>\"stone\",\"seats\"=>\"2\"", "area": null, "centroid_x": 134.6916428, "centroid_y": 34.837825 }, "geometry": { "type": "Point", "coordinates": [ 134.691642800000011, 34.837825 ] } },
{ "type": "Feature", "properties": { "osm_id": "2483278005", "name": null, "barrier": null, "highway": null, "ref": null, "address": null, "is_in": null, "place": null, "man_made": null, "other_tags": "\"amenity\"=>\"bench\",\"backrest\"=>\"no\",\"material\"=>\"stone\",\"seats\"=>\"2\"", "area": null, "centroid_x": 134.6916616, "centroid_y": 34.8378975 }, "geometry": { "type": "Point", "coordinates": [ 134.6916616, 34.8378975 ] } },
{ "type": "Feature", "properties": { "osm_id": "2483278006", "name": null, "barrier": null, "highway": null, "ref": null, "address": null, "is_in": null, "place": null, "man_made": null, "other_tags": "\"amenity\"=>\"waste_basket\",\"smoking\"=>\"yes\",\"waste\"=>\"cigarettes\"", "area": null, "centroid_x": 134.6928006, "centroid_y": 34.8382076 }, "geometry": { "type": "Point", "coordinates": [ 134.6928006, 34.8382076 ] } },
{ "type": "Feature", "properties": { "osm_id": "2484426563", "name": null, "barrier": null, "highway": null, "ref": null, "address": null, "is_in": null, "place": null, "man_made": "lamp", "other_tags": null, "area": null, "centroid_x": 134.6920805, "centroid_y": 34.8378713 }, "geometry": { "type": "Point", "coordinates": [ 134.6920805, 34.8378713 ] } },
{ "type": "Feature", "properties": { "osm_id": "2484436935", "name": "五輪塔供養塚", "barrier": null, "highway": null, "ref": null, "address": null, "is_in": null, "place": null, "man_made": null, "other_tags": "\"historic\"=>\"archaeological_site\"", "area": null, "centroid_x": 134.6934968, "centroid_y": 34.8383461 }, "geometry": { "type": "Point", "coordinates": [ 134.6934968, 34.8383461 ] } },
{ "type": "Feature", "properties": { "osm_id": "2484445915", "name": "鷺山口門跡", "barrier": null, "highway": null, "ref": null, "address": null, "is_in": null, "place": null, "man_made": null, "other_tags": "\"historic\"=>\"archaeological_site\"", "area": null, "centroid_x": 134.6912754, "centroid_y": 34.8380622 }, "geometry": { "type": "Point", "coordinates": [ 134.6912754, 34.8380622 ] } },
{ "type": "Feature", "properties": { "osm_id": "2830645120", "name": "お菊井戸", "barrier": null, "highway": null, "ref": null, "address": null, "is_in": null, "place": null, "man_made": null, "other_tags": "\"description\"=>\"案内板：お菊井(Okiku Well)の説明板\",\"information\"=>\"board\",\"name:en\"=>\"Okiku Well\",\"name:ja\"=>\"お菊井戸\",\"tourism\"=>\"information\"", "area": null, "centroid_x": 134.6938648, "centroid_y": 34.8386091 }, "geometry": { "type": "Point", "coordinates": [ 134.6938648, 34.8386091 ] } },
{ "type": "Feature", "properties": { "osm_id": "2857361711", "name": null, "barrier": null, "highway": null, "ref": null, "address": null, "is_in": null, "place": null, "man_made": null, "other_tags": "\"amenity\"=>\"vending_machine\",\"check_date\"=>\"2025-04-17\"", "area": null, "centroid_x": 134.6926065, "centroid_y": 34.8376304 }, "geometry": { "type": "Point", "coordinates": [ 134.692606500000011, 34.8376304 ] } },
{ "type": "Feature", "properties": { "osm_id": "2861292035", "name": "姫路城三の丸", "barrier": null, "highway": null, "ref": null, "address": null, "is_in": null, "place": null, "man_made": null, "other_tags": "\"board_type\"=>\"notice\",\"check_date\"=>\"2025-04-17\",\"information\"=>\"board\",\"tourism\"=>\"information\"", "area": null, "centroid_x": 134.693232, "centroid_y": 34.836228 }, "geometry": { "type": "Point", "coordinates": [ 134.693232, 34.836228 ] } },
{ "type": "Feature", "properties": { "osm_id": "2861292089", "name": "史跡姫路城", "barrier": null, "highway": null, "ref": null, "address": null, "is_in": null, "place": null, "man_made": null, "other_tags": "\"historic\"=>\"memorial\",\"memorial\"=>\"obelisk\",\"name:en\"=>\"Historic Places Himeji Castle\",\"name:ja\"=>\"史跡姫路城\",\"source_ref\"=>\"https://plus.google.com/photos?pid=6012914127859219874&oid=110468748131645597665\"", "area": null, "centroid_x": 134.6929199, "centroid_y": 34.8360928 }, "geometry": { "type": "Point", "coordinates": [ 134.6929199, 34.8360928 ] } },
{ "type": "Feature", "properties": { "osm_id": "2861292090", "name": "観光レンタサイクル駐輪場", "barrier": null, "highway": null, "ref": null, "address": null, "is_in": null, "place": null, "man_made": null, "other_tags": "\"access\"=>\"private\",\"amenity\"=>\"bicycle_parking\",\"source_ref\"=>\"https://plus.google.com/photos?pid=6012914127935677698&oid=110468748131645597665\"", "area": null, "centroid_x": 134.6940423, "centroid_y": 34.8371079 }, "geometry": { "type": "Point", "coordinates": [ 134.6940423, 34.8371079 ] } },
{ "type": "Feature", "properties": { "osm_id": "2861292091", "name": "観光レンタサイクル駐輪場", "barrier": null, "highway": null, "ref": null, "address": null, "is_in": null, "place": null, "man_made": null, "other_tags": "\"access\"=>\"private\",\"amenity\"=>\"bicycle_parking\",\"source_ref\"=>\"https://plus.google.com/photos?pid=6012914127935677698&oid=110468748131645597665\"", "area": null, "centroid_x": 134.6923659, "centroid_y": 34.8381437 }, "geometry": { "type": "Point", "coordinates": [ 134.6923659, 34.8381437 ] } },
{ "type": "Feature", "properties": { "osm_id": "3085267722", "name": "姫路城", "barrier": null, "highway": null, "ref": null, "address": null, "is_in": null, "place": null, "man_made": "survey_point", "other_tags": "\"type\"=>\"triangulation\"", "area": null, "centroid_x": 134.6939653, "centroid_y": 34.8387884 }, "geometry": { "type": "Point", "coordinates": [ 134.6939653, 34.8387884 ] } },
{ "type": "Feature", "properties": { "osm_id": "3673521390", "name": "いノ門", "barrier": "gate", "highway": null, "ref": null, "address": null, "is_in": null, "place": null, "man_made": null, "other_tags": "\"bicycle\"=>\"no\",\"foot\"=>\"yes\"", "area": null, "centroid_x": 134.6925039, "centroid_y": 34.8391468 }, "geometry": { "type": "Point", "coordinates": [ 134.6925039, 34.8391468 ] } },
{ "type": "Feature", "properties": { "osm_id": "4167759495", "name": null, "barrier": "gate", "highway": null, "ref": null, "address": null, "is_in": null, "place": null, "man_made": null, "other_tags": "\"bicycle\"=>\"no\",\"foot\"=>\"yes\"", "area": null, "centroid_x": 134.6927105, "centroid_y": 34.8382898 }, "geometry": { "type": "Point", "coordinates": [ 134.6927105, 34.8382898 ] } },
{ "type": "Feature", "properties": { "osm_id": "4167759496", "name": null, "barrier": "gate", "highway": null, "ref": null, "address": null, "is_in": null, "place": null, "man_made": null, "other_tags": "\"bicycle\"=>\"no\",\"foot\"=>\"yes\"", "area": null, "centroid_x": 134.6926415, "centroid_y": 34.8382904 }, "geometry": { "type": "Point", "coordinates": [ 134.6926415, 34.8382904 ] } },
{ "type": "Feature", "properties": { "osm_id": "4316663478", "name": "世界文化遺産 国宝 姫路城", "barrier": null, "highway": null, "ref": null, "address": null, "is_in": null, "place": null, "man_made": null, "other_tags": "\"board_type\"=>\"history\",\"check_date\"=>\"2023-02-08\",\"information\"=>\"board\",\"tourism\"=>\"information\"", "area": null, "centroid_x": 134.6930369, "centroid_y": 34.8359336 }, "geometry": { "type": "Point", "coordinates": [ 134.69303690000001, 34.8359336 ] } },
{ "type": "Feature", "properties": { "osm_id": "4460325234", "name": null, "barrier": null, "highway": null, "ref": null, "address": null, "is_in": null, "place": null, "man_made": null, "other_tags": "\"natural\"=>\"tree\"", "area": null, "centroid_x": 134.6935041, "centroid_y": 34.8364727 }, "geometry": { "type": "Point", "coordinates": [ 134.693504100000013, 34.8364727 ] } },
{ "type": "Feature", "properties": { "osm_id": "4460325303", "name": null, "barrier": null, "highway": null, "ref": null, "address": null, "is_in": null, "place": null, "man_made": "water_well", "other_tags": null, "area": null, "centroid_x": 134.692264, "centroid_y": 34.8376918 }, "geometry": { "type": "Point", "coordinates": [ 134.692264, 34.8376918 ] } },
{ "type": "Feature", "properties": { "osm_id": "4460325338", "name": "下山里　上山里下段石垣", "barrier": null, "highway": null, "ref": null, "address": null, "is_in": null, "place": null, "man_made": null, "other_tags": "\"information\"=>\"board\",\"tourism\"=>\"information\"", "area": null, "centroid_x": 134.693544, "centroid_y": 34.8383076 }, "geometry": { "type": "Point", "coordinates": [ 134.693544, 34.8383076 ] } },
{ "type": "Feature", "properties": { "osm_id": "4460325339", "name": "天守の庭", "barrier": null, "highway": null, "ref": null, "address": null, "is_in": null, "place": null, "man_made": null, "other_tags": "\"information\"=>\"board\",\"name:en\"=>\"The Garden of the Main Keep\",\"tourism\"=>\"information\"", "area": null, "centroid_x": 134.6930066, "centroid_y": 34.8381965 }, "geometry": { "type": "Point", "coordinates": [ 134.6930066, 34.8381965 ] } },
{ "type": "Feature", "properties": { "osm_id": "4460325340", "name": "姫路城の歴史", "barrier": null, "highway": null, "ref": null, "address": null, "is_in": null, "place": null, "man_made": null, "other_tags": "\"check_date\"=>\"2025-04-17\",\"information\"=>\"board\",\"name:en\"=>\"History of Himeji Castle\",\"tourism\"=>\"information\"", "area": null, "centroid_x": 134.692728, "centroid_y": 34.8381901 }, "geometry": { "type": "Point", "coordinates": [ 134.692728, 34.8381901 ] } },
{ "type": "Feature", "properties": { "osm_id": "4460325341", "name": "姫路城三の丸広場", "barrier": null, "highway": null, "ref": null, "address": null, "is_in": null, "place": null, "man_made": null, "other_tags": "\"check_date\"=>\"2025-04-17\",\"information\"=>\"board\",\"tourism\"=>\"information\"", "area": null, "centroid_x": 134.693476, "centroid_y": 34.8364969 }, "geometry": { "type": "Point", "coordinates": [ 134.693476, 34.8364969 ] } },
{ "type": "Feature", "properties": { "osm_id": "4460325342", "name": "姫路城入城口", "barrier": null, "highway": null, "ref": null, "address": null, "is_in": null, "place": null, "man_made": null, "other_tags": "\"check_date\"=>\"2025-04-17\",\"information\"=>\"board\",\"tourism\"=>\"information\"", "area": null, "centroid_x": 134.692561, "centroid_y": 34.8381816 }, "geometry": { "type": "Point", "coordinates": [ 134.692561, 34.8381816 ] } },
{ "type": "Feature", "properties": { "osm_id": "4571563236", "name": null, "barrier": null, "highway": null, "ref": null, "address": null, "is_in": null, "place": null, "man_made": null, "other_tags": "\"amenity\"=>\"bench\",\"backrest\"=>\"yes\"", "area": null, "centroid_x": 134.6924911, "centroid_y": 34.837496 }, "geometry": { "type": "Point", "coordinates": [ 134.692491100000012, 34.837496 ] } },
{ "type": "Feature", "properties": { "osm_id": "4571563237", "name": null, "barrier": null, "highway": null, "ref": null, "address": null, "is_in": null, "place": null, "man_made": null, "other_tags": "\"amenity\"=>\"bench\",\"backrest\"=>\"yes\"", "area": null, "centroid_x": 134.6924899, "centroid_y": 34.8374636 }, "geometry": { "type": "Point", "coordinates": [ 134.6924899, 34.8374636 ] } },
{ "type": "Feature", "properties": { "osm_id": "4571563238", "name": null, "barrier": null, "highway": null, "ref": null, "address": null, "is_in": null, "place": null, "man_made": null, "other_tags": "\"amenity\"=>\"bench\",\"backrest\"=>\"yes\"", "area": null, "centroid_x": 134.6924931, "centroid_y": 34.8374289 }, "geometry": { "type": "Point", "coordinates": [ 134.6924931, 34.8374289 ] } },
{ "type": "Feature", "properties": { "osm_id": "4571563239", "name": null, "barrier": null, "highway": null, "ref": null, "address": null, "is_in": null, "place": null, "man_made": null, "other_tags": "\"amenity\"=>\"bench\",\"backrest\"=>\"yes\"", "area": null, "centroid_x": 134.6924949, "centroid_y": 34.8373892 }, "geometry": { "type": "Point", "coordinates": [ 134.692494900000014, 34.8373892 ] } },
{ "type": "Feature", "properties": { "osm_id": "4571563240", "name": null, "barrier": null, "highway": null, "ref": null, "address": null, "is_in": null, "place": null, "man_made": null, "other_tags": "\"amenity\"=>\"bench\",\"backrest\"=>\"yes\"", "area": null, "centroid_x": 134.6925551, "centroid_y": 34.8374004 }, "geometry": { "type": "Point", "coordinates": [ 134.6925551, 34.8374004 ] } },
{ "type": "Feature", "properties": { "osm_id": "4571563241", "name": null, "barrier": null, "highway": null, "ref": null, "address": null, "is_in": null, "place": null, "man_made": null, "other_tags": "\"amenity\"=>\"bench\",\"backrest\"=>\"yes\"", "area": null, "centroid_x": 134.6926192, "centroid_y": 34.8374933 }, "geometry": { "type": "Point", "coordinates": [ 134.6926192, 34.8374933 ] } },
{ "type": "Feature", "properties": { "osm_id": "4571563242", "name": null, "barrier": null, "highway": null, "ref": null, "address": null, "is_in": null, "place": null, "man_made": null, "other_tags": "\"amenity\"=>\"bench\",\"backrest\"=>\"yes\"", "area": null, "centroid_x": 134.6926148, "centroid_y": 34.8374498 }, "geometry": { "type": "Point", "coordinates": [ 134.6926148, 34.8374498 ] } },
{ "type": "Feature", "properties": { "osm_id": "4571563243", "name": null, "barrier": null, "highway": null, "ref": null, "address": null, "is_in": null, "place": null, "man_made": null, "other_tags": "\"amenity\"=>\"bench\",\"backrest\"=>\"yes\"", "area": null, "centroid_x": 134.6924987, "centroid_y": 34.8373079 }, "geometry": { "type": "Point", "coordinates": [ 134.692498699999987, 34.8373079 ] } },
{ "type": "Feature", "properties": { "osm_id": "4571563244", "name": null, "barrier": null, "highway": null, "ref": null, "address": null, "is_in": null, "place": null, "man_made": null, "other_tags": "\"amenity\"=>\"bench\",\"backrest\"=>\"yes\"", "area": null, "centroid_x": 134.6925443, "centroid_y": 34.8372463 }, "geometry": { "type": "Point", "coordinates": [ 134.6925443, 34.8372463 ] } },
{ "type": "Feature", "properties": { "osm_id": "5311692191", "name": null, "barrier": null, "highway": null, "ref": null, "address": null, "is_in": null, "place": null, "man_made": null, "other_tags": "\"shop\"=>\"gift\"", "area": null, "centroid_x": 134.6925536, "centroid_y": 34.8375809 }, "geometry": { "type": "Point", "coordinates": [ 134.6925536, 34.8375809 ] } },
{ "type": "Feature", "properties": { "osm_id": "5479947793", "name": "二の櫓", "barrier": null, "highway": null, "ref": null, "address": null, "is_in": null, "place": null, "man_made": null, "other_tags": "\"historic\"=>\"memorial\"", "area": null, "centroid_x": 134.6935435, "centroid_y": 34.8395367 }, "geometry": { "type": "Point", "coordinates": [ 134.6935435, 34.8395367 ] } },
{ "type": "Feature", "properties": { "osm_id": "5481771779", "name": "との一門", "barrier": null, "highway": null, "ref": null, "address": null, "is_in": null, "place": null, "man_made": null, "other_tags": "\"information\"=>\"board\",\"tourism\"=>\"information\"", "area": null, "centroid_x": 134.6944183, "centroid_y": 34.839471 }, "geometry": { "type": "Point", "coordinates": [ 134.6944183, 34.839471 ] } },
{ "type": "Feature", "properties": { "osm_id": "5482680722", "name": "菱の門", "barrier": null, "highway": null, "ref": null, "address": null, "is_in": null, "place": null, "man_made": null, "other_tags": "\"information\"=>\"board\",\"tourism\"=>\"information\"", "area": null, "centroid_x": 134.6923957, "centroid_y": 34.8386094 }, "geometry": { "type": "Point", "coordinates": [ 134.6923957, 34.8386094 ] } },
{ "type": "Feature", "properties": { "osm_id": "5654015448", "name": null, "barrier": null, "highway": null, "ref": null, "address": null, "is_in": null, "place": null, "man_made": null, "other_tags": "\"check_date\"=>\"2025-04-17\",\"information\"=>\"map\",\"tourism\"=>\"information\"", "area": null, "centroid_x": 134.6926206, "centroid_y": 34.8378713 }, "geometry": { "type": "Point", "coordinates": [ 134.6926206, 34.8378713 ] } },
{ "type": "Feature", "properties": { "osm_id": "5654015449", "name": null, "barrier": null, "highway": null, "ref": null, "address": null, "is_in": null, "place": null, "man_made": "telescope", "other_tags": "\"telescope:type\"=>\"optical\",\"tourism\"=>\"viewpoint\"", "area": null, "centroid_x": 134.6937423, "centroid_y": 34.838823 }, "geometry": { "type": "Point", "coordinates": [ 134.6937423, 34.838823 ] } },
{ "type": "Feature", "properties": { "osm_id": "5654015450", "name": null, "barrier": null, "highway": null, "ref": null, "address": null, "is_in": null, "place": null, "man_made": null, "other_tags": "\"emergency\"=>\"fire_hydrant\",\"fire_hydrant:type\"=>\"pillar\"", "area": null, "centroid_x": 134.6938047, "centroid_y": 34.8383856 }, "geometry": { "type": "Point", "coordinates": [ 134.693804699999987, 34.8383856 ] } },
{ "type": "Feature", "properties": { "osm_id": "6515721363", "name": "狭間", "barrier": null, "highway": null, "ref": null, "address": null, "is_in": null, "place": null, "man_made": null, "other_tags": "\"board_type\"=>\"history\",\"check_date\"=>\"2023-10-01\",\"information\"=>\"board\",\"tourism\"=>\"information\"", "area": null, "centroid_x": 134.6923245, "centroid_y": 34.8391398 }, "geometry": { "type": "Point", "coordinates": [ 134.692324500000012, 34.8391398 ] } },
{ "type": "Feature", "properties": { "osm_id": "6515721364", "name": "西の丸 北門跡", "barrier": null, "highway": null, "ref": null, "address": null, "is_in": null, "place": null, "man_made": null, "other_tags": "\"board_type\"=>\"history\",\"check_date\"=>\"2023-10-01\",\"information\"=>\"board\",\"tourism\"=>\"information\"", "area": null, "centroid_x": 134.6923188, "centroid_y": 34.8391907 }, "geometry": { "type": "Point", "coordinates": [ 134.69231880000001, 34.8391907 ] } },
{ "type": "Feature", "properties": { "osm_id": "6515721366", "name": null, "barrier": null, "highway": null, "ref": null, "address": null, "is_in": null, "place": null, "man_made": null, "other_tags": "\"historic\"=>\"memorial\",\"memorial\"=>\"stele\"", "area": null, "centroid_x": 134.6921954, "centroid_y": 34.8391918 }, "geometry": { "type": "Point", "coordinates": [ 134.6921954, 34.8391918 ] } },
{ "type": "Feature", "properties": { "osm_id": "6515726789", "name": null, "barrier": null, "highway": null, "ref": null, "address": null, "is_in": null, "place": null, "man_made": "tower", "other_tags": null, "area": null, "centroid_x": 134.6915849, "centroid_y": 34.8388179 }, "geometry": { "type": "Point", "coordinates": [ 134.6915849, 34.8388179 ] } },
{ "type": "Feature", "properties": { "osm_id": "6515726832", "name": "百閒廊下", "barrier": null, "highway": null, "ref": null, "address": null, "is_in": null, "place": null, "man_made": null, "other_tags": "\"board_type\"=>\"history\",\"check_date\"=>\"2023-10-01\",\"information\"=>\"board\",\"tourism\"=>\"information\"", "area": null, "centroid_x": 134.6914434, "centroid_y": 34.8383935 }, "geometry": { "type": "Point", "coordinates": [ 134.6914434, 34.8383935 ] } },
{ "type": "Feature", "properties": { "osm_id": "6515726833", "name": "西の丸", "barrier": null, "highway": null, "ref": null, "address": null, "is_in": null, "place": null, "man_made": null, "other_tags": "\"check_date\"=>\"2023-10-01\",\"information\"=>\"board\",\"tourism\"=>\"information\"", "area": null, "centroid_x": 134.6917156, "centroid_y": 34.8385229 }, "geometry": { "type": "Point", "coordinates": [ 134.6917156, 34.8385229 ] } },
{ "type": "Feature", "properties": { "osm_id": "6515727001", "name": "武者溜り", "barrier": null, "highway": null, "ref": null, "address": null, "is_in": null, "place": null, "man_made": null, "other_tags": "\"information\"=>\"board\",\"tourism\"=>\"information\"", "area": null, "centroid_x": 134.6922127, "centroid_y": 34.8385351 }, "geometry": { "type": "Point", "coordinates": [ 134.6922127, 34.8385351 ] } },
{ "type": "Feature", "properties": { "osm_id": "6515727007", "name": "西の丸 南門跡", "barrier": null, "highway": null, "ref": null, "address": null, "is_in": null, "place": null, "man_made": null, "other_tags": "\"board_type\"=>\"history\",\"check_date\"=>\"2023-10-01\",\"information\"=>\"board\",\"tourism\"=>\"information\"", "area": null, "centroid_x": 134.6922286, "centroid_y": 34.8385864 }, "geometry": { "type": "Point", "coordinates": [ 134.6922286, 34.8385864 ] } },
{ "type": "Feature", "properties": { "osm_id": "6515727027", "name": "世界遺産姫路城", "barrier": null, "highway": null, "ref": null, "address": null, "is_in": null, "place": null, "man_made": null, "other_tags": "\"check_date\"=>\"2023-10-01\",\"information\"=>\"board\",\"tourism\"=>\"information\"", "area": null, "centroid_x": 134.6923801, "centroid_y": 34.8388179 }, "geometry": { "type": "Point", "coordinates": [ 134.6923801, 34.8388179 ] } },
{ "type": "Feature", "properties": { "osm_id": "6515727028", "name": "中村大佐顕彰碑", "barrier": null, "highway": null, "ref": null, "address": null, "is_in": null, "place": null, "man_made": null, "other_tags": "\"historic\"=>\"memorial\",\"memorial\"=>\"stele\"", "area": null, "centroid_x": 134.6922849, "centroid_y": 34.8388476 }, "geometry": { "type": "Point", "coordinates": [ 134.6922849, 34.8388476 ] } },
{ "type": "Feature", "properties": { "osm_id": "6515727046", "name": "国宝・重要文化財一覧", "barrier": null, "highway": null, "ref": null, "address": null, "is_in": null, "place": null, "man_made": null, "other_tags": "\"information\"=>\"board\",\"tourism\"=>\"information\"", "area": null, "centroid_x": 134.6926353, "centroid_y": 34.8385713 }, "geometry": { "type": "Point", "coordinates": [ 134.6926353, 34.8385713 ] } },
{ "type": "Feature", "properties": { "osm_id": "6515727084", "name": null, "barrier": null, "highway": null, "ref": null, "address": null, "is_in": null, "place": null, "man_made": null, "other_tags": "\"amenity\"=>\"bench\",\"backrest\"=>\"no\",\"material\"=>\"stone\",\"seats\"=>\"2\"", "area": null, "centroid_x": 134.6922145, "centroid_y": 34.8376748 }, "geometry": { "type": "Point", "coordinates": [ 134.6922145, 34.8376748 ] } },
{ "type": "Feature", "properties": { "osm_id": "6515727085", "name": null, "barrier": null, "highway": null, "ref": null, "address": null, "is_in": null, "place": null, "man_made": null, "other_tags": "\"amenity\"=>\"bench\",\"backrest\"=>\"no\",\"material\"=>\"stone\",\"seats\"=>\"2\"", "area": null, "centroid_x": 134.6922175, "centroid_y": 34.8377126 }, "geometry": { "type": "Point", "coordinates": [ 134.6922175, 34.8377126 ] } },
{ "type": "Feature", "properties": { "osm_id": "6515819602", "name": "姥ヶ石", "barrier": null, "highway": null, "ref": null, "address": null, "is_in": null, "place": null, "man_made": null, "other_tags": "\"information\"=>\"board\",\"tourism\"=>\"information\"", "area": null, "centroid_x": 134.6937065, "centroid_y": 34.8396131 }, "geometry": { "type": "Point", "coordinates": [ 134.6937065, 34.8396131 ] } },
{ "type": "Feature", "properties": { "osm_id": "6515819609", "name": null, "barrier": null, "highway": null, "ref": null, "address": null, "is_in": null, "place": null, "man_made": "water_well", "other_tags": null, "area": null, "centroid_x": 134.6938607, "centroid_y": 34.8397482 }, "geometry": { "type": "Point", "coordinates": [ 134.693860699999988, 34.8397482 ] } },
{ "type": "Feature", "properties": { "osm_id": "6515819628", "name": "油壁", "barrier": null, "highway": null, "ref": null, "address": null, "is_in": null, "place": null, "man_made": null, "other_tags": "\"information\"=>\"board\",\"tourism\"=>\"information\"", "area": null, "centroid_x": 134.6936622, "centroid_y": 34.839683 }, "geometry": { "type": "Point", "coordinates": [ 134.6936622, 34.839683 ] } },
{ "type": "Feature", "properties": { "osm_id": "6515819656", "name": "にの門", "barrier": null, "highway": null, "ref": null, "address": null, "is_in": null, "place": null, "man_made": null, "other_tags": "\"information\"=>\"board\",\"tourism\"=>\"information\"", "area": null, "centroid_x": 134.6934004, "centroid_y": 34.8395105 }, "geometry": { "type": "Point", "coordinates": [ 134.6934004, 34.8395105 ] } },
{ "type": "Feature", "properties": { "osm_id": "6515825694", "name": "十字紋の鬼瓦", "barrier": null, "highway": null, "ref": null, "address": null, "is_in": null, "place": null, "man_made": null, "other_tags": "\"information\"=>\"board\",\"tourism\"=>\"information\"", "area": null, "centroid_x": 134.6930728, "centroid_y": 34.8396613 }, "geometry": { "type": "Point", "coordinates": [ 134.69307280000001, 34.8396613 ] } },
{ "type": "Feature", "properties": { "osm_id": "6515825730", "name": "石灯籠の基礎", "barrier": null, "highway": null, "ref": null, "address": null, "is_in": null, "place": null, "man_made": null, "other_tags": "\"information\"=>\"board\",\"tourism\"=>\"information\"", "area": null, "centroid_x": 134.6930383, "centroid_y": 34.839538 }, "geometry": { "type": "Point", "coordinates": [ 134.693038300000012, 34.839538 ] } },
{ "type": "Feature", "properties": { "osm_id": "6515825747", "name": "姫路城案内図", "barrier": null, "highway": null, "ref": null, "address": null, "is_in": null, "place": null, "man_made": null, "other_tags": "\"check_date\"=>\"2023-10-01\",\"information\"=>\"map\",\"tourism\"=>\"information\"", "area": null, "centroid_x": 134.6925618, "centroid_y": 34.8395218 }, "geometry": { "type": "Point", "coordinates": [ 134.6925618, 34.8395218 ] } },
{ "type": "Feature", "properties": { "osm_id": "6515844848", "name": "備前丸", "barrier": null, "highway": null, "ref": null, "address": null, "is_in": null, "place": null, "man_made": null, "other_tags": "\"information\"=>\"board\",\"tourism\"=>\"information\"", "area": null, "centroid_x": 134.693626, "centroid_y": 34.8390292 }, "geometry": { "type": "Point", "coordinates": [ 134.693626, 34.8390292 ] } },
{ "type": "Feature", "properties": { "osm_id": "6515844849", "name": null, "barrier": null, "highway": null, "ref": null, "address": null, "is_in": null, "place": null, "man_made": null, "other_tags": "\"natural\"=>\"tree\"", "area": null, "centroid_x": 134.6935732, "centroid_y": 34.8390424 }, "geometry": { "type": "Point", "coordinates": [ 134.6935732, 34.8390424 ] } },
{ "type": "Feature", "properties": { "osm_id": "6515844850", "name": null, "barrier": null, "highway": null, "ref": null, "address": null, "is_in": null, "place": null, "man_made": "water_well", "other_tags": null, "area": null, "centroid_x": 134.6934641, "centroid_y": 34.8390669 }, "geometry": { "type": "Point", "coordinates": [ 134.6934641, 34.8390669 ] } },
{ "type": "Feature", "properties": { "osm_id": "6515844876", "name": "刑部大神", "barrier": null, "highway": null, "ref": null, "address": null, "is_in": null, "place": null, "man_made": null, "other_tags": "\"historic\"=>\"wayside_shrine\",\"name:en\"=>\"Himeji Castle\",\"religion\"=>\"shinto\"", "area": null, "centroid_x": 134.6940136, "centroid_y": 34.8393319 }, "geometry": { "type": "Point", "coordinates": [ 134.6940136, 34.8393319 ] } },
{ "type": "Feature", "properties": { "osm_id": "6515890987", "name": "水四門", "barrier": "gate", "highway": null, "ref": null, "address": null, "is_in": null, "place": null, "man_made": null, "other_tags": null, "area": null, "centroid_x": 134.6936849, "centroid_y": 34.8392827 }, "geometry": { "type": "Point", "coordinates": [ 134.6936849, 34.8392827 ] } },
{ "type": "Feature", "properties": { "osm_id": "6515891010", "name": "水三門", "barrier": "gate", "highway": null, "ref": null, "address": null, "is_in": null, "place": null, "man_made": null, "other_tags": null, "area": null, "centroid_x": 134.6935508, "centroid_y": 34.8393439 }, "geometry": { "type": "Point", "coordinates": [ 134.6935508, 34.8393439 ] } },
{ "type": "Feature", "properties": { "osm_id": "6516084390", "name": "姫路城大天守 西心柱二代目檜", "barrier": null, "highway": null, "ref": null, "address": null, "is_in": null, "place": null, "man_made": null, "other_tags": "\"historic\"=>\"memorial\",\"memorial\"=>\"stele\"", "area": null, "centroid_x": 134.6948558, "centroid_y": 34.8387628 }, "geometry": { "type": "Point", "coordinates": [ 134.6948558, 34.8387628 ] } },
{ "type": "Feature", "properties": { "osm_id": "6516084396", "name": "特別史跡姫路城跡 内船場蔵南石垣について", "barrier": null, "highway": null, "ref": null, "address": null, "is_in": null, "place": null, "man_made": null, "other_tags": "\"information\"=>\"board\",\"tourism\"=>\"information\"", "area": null, "centroid_x": 134.6944521, "centroid_y": 34.8385064 }, "geometry": { "type": "Point", "coordinates": [ 134.6944521, 34.8385064 ] } },
{ "type": "Feature", "properties": { "osm_id": "6516084447", "name": "姫山・鷺山と三国堀", "barrier": null, "highway": null, "ref": null, "address": null, "is_in": null, "place": null, "man_made": null, "other_tags": "\"check_date\"=>\"2025-04-17\",\"information\"=>\"board\",\"tourism\"=>\"information\"", "area": null, "centroid_x": 134.6927577, "centroid_y": 34.8387392 }, "geometry": { "type": "Point", "coordinates": [ 134.692757699999987, 34.8387392 ] } },
{ "type": "Feature", "properties": { "osm_id": "6516084477", "name": "井戸", "barrier": null, "highway": null, "ref": null, "address": null, "is_in": null, "place": null, "man_made": null, "other_tags": "\"information\"=>\"board\",\"tourism\"=>\"information\"", "area": null, "centroid_x": 134.6926524, "centroid_y": 34.8391847 }, "geometry": { "type": "Point", "coordinates": [ 134.692652399999986, 34.8391847 ] } },
{ "type": "Feature", "properties": { "osm_id": "6516084478", "name": null, "barrier": null, "highway": null, "ref": null, "address": null, "is_in": null, "place": null, "man_made": "water_well", "other_tags": null, "area": null, "centroid_x": 134.6926876, "centroid_y": 34.8391979 }, "geometry": { "type": "Point", "coordinates": [ 134.6926876, 34.8391979 ] } },
{ "type": "Feature", "properties": { "osm_id": "6516084527", "name": "をの門跡", "barrier": null, "highway": null, "ref": null, "address": null, "is_in": null, "place": null, "man_made": null, "other_tags": "\"information\"=>\"board\",\"tourism\"=>\"information\"", "area": null, "centroid_x": 134.6932016, "centroid_y": 34.839046 }, "geometry": { "type": "Point", "coordinates": [ 134.6932016, 34.839046 ] } },
{ "type": "Feature", "properties": { "osm_id": "6516084532", "name": "姫路城案内図", "barrier": null, "highway": null, "ref": null, "address": null, "is_in": null, "place": null, "man_made": null, "other_tags": "\"information\"=>\"map\",\"tourism\"=>\"information\"", "area": null, "centroid_x": 134.6932733, "centroid_y": 34.8388795 }, "geometry": { "type": "Point", "coordinates": [ 134.693273299999987, 34.8388795 ] } },
{ "type": "Feature", "properties": { "osm_id": "6516084555", "name": "継ぎ目のある石垣", "barrier": null, "highway": null, "ref": null, "address": null, "is_in": null, "place": null, "man_made": null, "other_tags": "\"information\"=>\"board\",\"tourism\"=>\"information\"", "area": null, "centroid_x": 134.6932673, "centroid_y": 34.8386902 }, "geometry": { "type": "Point", "coordinates": [ 134.6932673, 34.8386902 ] } },
{ "type": "Feature", "properties": { "osm_id": "6516084562", "name": "るの門跡", "barrier": null, "highway": null, "ref": null, "address": null, "is_in": null, "place": null, "man_made": null, "other_tags": "\"information\"=>\"board\",\"tourism\"=>\"information\"", "area": null, "centroid_x": 134.6932123, "centroid_y": 34.8388005 }, "geometry": { "type": "Point", "coordinates": [ 134.6932123, 34.8388005 ] } },
{ "type": "Feature", "properties": { "osm_id": "6516084567", "name": "扇の勾配", "barrier": null, "highway": null, "ref": null, "address": null, "is_in": null, "place": null, "man_made": null, "other_tags": "\"information\"=>\"board\",\"tourism\"=>\"information\"", "area": null, "centroid_x": 134.6933967, "centroid_y": 34.838923 }, "geometry": { "type": "Point", "coordinates": [ 134.6933967, 34.838923 ] } },
{ "type": "Feature", "properties": { "osm_id": "6516084568", "name": "ぬの門", "barrier": null, "highway": null, "ref": null, "address": null, "is_in": null, "place": null, "man_made": null, "other_tags": "\"information\"=>\"board\",\"tourism\"=>\"information\"", "area": null, "centroid_x": 134.6935077, "centroid_y": 34.8387793 }, "geometry": { "type": "Point", "coordinates": [ 134.6935077, 34.8387793 ] } },
{ "type": "Feature", "properties": { "osm_id": "6516084573", "name": "石棺", "barrier": null, "highway": null, "ref": null, "address": null, "is_in": null, "place": null, "man_made": null, "other_tags": "\"information\"=>\"board\",\"tourism\"=>\"information\"", "area": null, "centroid_x": 134.6935439, "centroid_y": 34.8385163 }, "geometry": { "type": "Point", "coordinates": [ 134.6935439, 34.8385163 ] } },
{ "type": "Feature", "properties": { "osm_id": "6516084576", "name": "お菊井", "barrier": null, "highway": null, "ref": null, "address": null, "is_in": null, "place": null, "man_made": null, "other_tags": "\"historic\"=>\"memorial\",\"memorial\"=>\"stele\"", "area": null, "centroid_x": 134.6938376, "centroid_y": 34.8386076 }, "geometry": { "type": "Point", "coordinates": [ 134.6938376, 34.8386076 ] } },
{ "type": "Feature", "properties": { "osm_id": "6516084640", "name": "帯の櫓", "barrier": null, "highway": null, "ref": null, "address": null, "is_in": null, "place": null, "man_made": null, "other_tags": "\"information\"=>\"board\",\"tourism\"=>\"information\"", "area": null, "centroid_x": 134.6944917, "centroid_y": 34.8390584 }, "geometry": { "type": "Point", "coordinates": [ 134.694491699999986, 34.8390584 ] } },
{ "type": "Feature", "properties": { "osm_id": "6516084641", "name": "石棺", "barrier": null, "highway": null, "ref": null, "address": null, "is_in": null, "place": null, "man_made": null, "other_tags": "\"information\"=>\"board\",\"tourism\"=>\"information\"", "area": null, "centroid_x": 134.6943837, "centroid_y": 34.8391398 }, "geometry": { "type": "Point", "coordinates": [ 134.6943837, 34.8391398 ] } },
{ "type": "Feature", "properties": { "osm_id": "7954900524", "name": null, "barrier": null, "highway": null, "ref": null, "address": null, "is_in": null, "place": null, "man_made": null, "other_tags": "\"natural\"=>\"tree\"", "area": null, "centroid_x": 134.6925785, "centroid_y": 34.8390261 }, "geometry": { "type": "Point", "coordinates": [ 134.6925785, 34.8390261 ] } },
{ "type": "Feature", "properties": { "osm_id": "7954900525", "name": null, "barrier": null, "highway": null, "ref": null, "address": null, "is_in": null, "place": null, "man_made": null, "other_tags": "\"natural\"=>\"tree\"", "area": null, "centroid_x": 134.6925649, "centroid_y": 34.8388941 }, "geometry": { "type": "Point", "coordinates": [ 134.6925649, 34.8388941 ] } },
{ "type": "Feature", "properties": { "osm_id": "7954900526", "name": null, "barrier": null, "highway": null, "ref": null, "address": null, "is_in": null, "place": null, "man_made": null, "other_tags": "\"natural\"=>\"tree\"", "area": null, "centroid_x": 134.6931255, "centroid_y": 34.8393288 }, "geometry": { "type": "Point", "coordinates": [ 134.6931255, 34.8393288 ] } },
{ "type": "Feature", "properties": { "osm_id": "7954900527", "name": null, "barrier": null, "highway": null, "ref": null, "address": null, "is_in": null, "place": null, "man_made": null, "other_tags": "\"natural\"=>\"tree\"", "area": null, "centroid_x": 134.6926268, "centroid_y": 34.8392994 }, "geometry": { "type": "Point", "coordinates": [ 134.6926268, 34.8392994 ] } },
{ "type": "Feature", "properties": { "osm_id": "7954900528", "name": null, "barrier": null, "highway": null, "ref": null, "address": null, "is_in": null, "place": null, "man_made": null, "other_tags": "\"natural\"=>\"tree\"", "area": null, "centroid_x": 134.6927085, "centroid_y": 34.8385173 }, "geometry": { "type": "Point", "coordinates": [ 134.6927085, 34.8385173 ] } },
{ "type": "Feature", "properties": { "osm_id": "7954900529", "name": null, "barrier": null, "highway": null, "ref": null, "address": null, "is_in": null, "place": null, "man_made": null, "other_tags": "\"natural\"=>\"tree\"", "area": null, "centroid_x": 134.6936564, "centroid_y": 34.8387072 }, "geometry": { "type": "Point", "coordinates": [ 134.6936564, 34.8387072 ] } },
{ "type": "Feature", "properties": { "osm_id": "7954900530", "name": null, "barrier": null, "highway": null, "ref": null, "address": null, "is_in": null, "place": null, "man_made": null, "other_tags": "\"natural\"=>\"tree\"", "area": null, "centroid_x": 134.6932258, "centroid_y": 34.8390993 }, "geometry": { "type": "Point", "coordinates": [ 134.6932258, 34.8390993 ] } },
{ "type": "Feature", "properties": { "osm_id": "7954900531", "name": null, "barrier": null, "highway": null, "ref": null, "address": null, "is_in": null, "place": null, "man_made": null, "other_tags": "\"natural\"=>\"tree\"", "area": null, "centroid_x": 134.6932802, "centroid_y": 34.8389652 }, "geometry": { "type": "Point", "coordinates": [ 134.6932802, 34.8389652 ] } },
{ "type": "Feature", "properties": { "osm_id": "7954900532", "name": null, "barrier": null, "highway": null, "ref": null, "address": null, "is_in": null, "place": null, "man_made": null, "other_tags": "\"natural\"=>\"tree\"", "area": null, "centroid_x": 134.6931527, "centroid_y": 34.8395137 }, "geometry": { "type": "Point", "coordinates": [ 134.693152700000013, 34.8395137 ] } },
{ "type": "Feature", "properties": { "osm_id": "7954900533", "name": null, "barrier": null, "highway": null, "ref": null, "address": null, "is_in": null, "place": null, "man_made": null, "other_tags": "\"natural\"=>\"tree\"", "area": null, "centroid_x": 134.6921058, "centroid_y": 34.8392953 }, "geometry": { "type": "Point", "coordinates": [ 134.6921058, 34.8392953 ] } },
{ "type": "Feature", "properties": { "osm_id": "7954900534", "name": null, "barrier": null, "highway": null, "ref": null, "address": null, "is_in": null, "place": null, "man_made": null, "other_tags": "\"natural\"=>\"tree\"", "area": null, "centroid_x": 134.6917494, "centroid_y": 34.8391429 }, "geometry": { "type": "Point", "coordinates": [ 134.6917494, 34.8391429 ] } },
{ "type": "Feature", "properties": { "osm_id": "7954900535", "name": null, "barrier": null, "highway": null, "ref": null, "address": null, "is_in": null, "place": null, "man_made": null, "other_tags": "\"natural\"=>\"tree\"", "area": null, "centroid_x": 134.6919202, "centroid_y": 34.8386615 }, "geometry": { "type": "Point", "coordinates": [ 134.6919202, 34.8386615 ] } },
{ "type": "Feature", "properties": { "osm_id": "7954900536", "name": null, "barrier": null, "highway": null, "ref": null, "address": null, "is_in": null, "place": null, "man_made": null, "other_tags": "\"natural\"=>\"tree\"", "area": null, "centroid_x": 134.6917457, "centroid_y": 34.8387336 }, "geometry": { "type": "Point", "coordinates": [ 134.691745700000013, 34.8387336 ] } },
{ "type": "Feature", "properties": { "osm_id": "7954900537", "name": null, "barrier": null, "highway": null, "ref": null, "address": null, "is_in": null, "place": null, "man_made": null, "other_tags": "\"natural\"=>\"tree\"", "area": null, "centroid_x": 134.691695, "centroid_y": 34.8388169 }, "geometry": { "type": "Point", "coordinates": [ 134.691695, 34.8388169 ] } },
{ "type": "Feature", "properties": { "osm_id": "7954900538", "name": null, "barrier": null, "highway": null, "ref": null, "address": null, "is_in": null, "place": null, "man_made": null, "other_tags": "\"natural\"=>\"tree\"", "area": null, "centroid_x": 134.691648, "centroid_y": 34.8385427 }, "geometry": { "type": "Point", "coordinates": [ 134.691648, 34.8385427 ] } },
{ "type": "Feature", "properties": { "osm_id": "7954900539", "name": null, "barrier": null, "highway": null, "ref": null, "address": null, "is_in": null, "place": null, "man_made": null, "other_tags": "\"natural\"=>\"tree\"", "area": null, "centroid_x": 134.6914883, "centroid_y": 34.8386595 }, "geometry": { "type": "Point", "coordinates": [ 134.6914883, 34.8386595 ] } },
{ "type": "Feature", "properties": { "osm_id": "7954900540", "name": null, "barrier": null, "highway": null, "ref": null, "address": null, "is_in": null, "place": null, "man_made": null, "other_tags": "\"natural\"=>\"tree\"", "area": null, "centroid_x": 134.6914091, "centroid_y": 34.838561 }, "geometry": { "type": "Point", "coordinates": [ 134.691409099999987, 34.838561 ] } },
{ "type": "Feature", "properties": { "osm_id": "7954900541", "name": null, "barrier": null, "highway": null, "ref": null, "address": null, "is_in": null, "place": null, "man_made": null, "other_tags": "\"natural\"=>\"tree\"", "area": null, "centroid_x": 134.6913819, "centroid_y": 34.8387377 }, "geometry": { "type": "Point", "coordinates": [ 134.69138190000001, 34.8387377 ] } },
{ "type": "Feature", "properties": { "osm_id": "7954900542", "name": null, "barrier": null, "highway": null, "ref": null, "address": null, "is_in": null, "place": null, "man_made": null, "other_tags": "\"natural\"=>\"tree\"", "area": null, "centroid_x": 134.6918101, "centroid_y": 34.8379881 }, "geometry": { "type": "Point", "coordinates": [ 134.6918101, 34.8379881 ] } },
{ "type": "Feature", "properties": { "osm_id": "7954900543", "name": null, "barrier": null, "highway": null, "ref": null, "address": null, "is_in": null, "place": null, "man_made": null, "other_tags": "\"natural\"=>\"tree\"", "area": null, "centroid_x": 134.692263, "centroid_y": 34.8383182 }, "geometry": { "type": "Point", "coordinates": [ 134.692263, 34.8383182 ] } },
{ "type": "Feature", "properties": { "osm_id": "9573853560", "name": null, "barrier": "gate", "highway": null, "ref": null, "address": null, "is_in": null, "place": null, "man_made": null, "other_tags": null, "area": null, "centroid_x": 134.6943855, "centroid_y": 34.8393065 }, "geometry": { "type": "Point", "coordinates": [ 134.69438550000001, 34.8393065 ] } },
{ "type": "Feature", "properties": { "osm_id": "9573853561", "name": null, "barrier": null, "highway": null, "ref": null, "address": null, "is_in": null, "place": null, "man_made": "water_well", "other_tags": null, "area": null, "centroid_x": 134.6944414, "centroid_y": 34.8392521 }, "geometry": { "type": "Point", "coordinates": [ 134.694441399999988, 34.8392521 ] } },
{ "type": "Feature", "properties": { "osm_id": "9574584917", "name": "棟門", "barrier": null, "highway": null, "ref": null, "address": null, "is_in": null, "place": null, "man_made": null, "other_tags": "\"information\"=>\"board\",\"tourism\"=>\"information\"", "area": null, "centroid_x": 134.6943854, "centroid_y": 34.8393097 }, "geometry": { "type": "Point", "coordinates": [ 134.694385399999987, 34.8393097 ] } },
{ "type": "Feature", "properties": { "osm_id": "9574584923", "name": "長壁神社遺趾", "barrier": null, "highway": null, "ref": null, "address": null, "is_in": null, "place": null, "man_made": null, "other_tags": "\"historic\"=>\"memorial\",\"memorial\"=>\"stele\"", "area": null, "centroid_x": 134.6946459, "centroid_y": 34.8395053 }, "geometry": { "type": "Point", "coordinates": [ 134.694645900000012, 34.8395053 ] } },
{ "type": "Feature", "properties": { "osm_id": "9574584924", "name": null, "barrier": "gate", "highway": null, "ref": null, "address": null, "is_in": null, "place": null, "man_made": null, "other_tags": "\"maxheight\"=>\"長壁神社跡\"", "area": null, "centroid_x": 134.6945482, "centroid_y": 34.8393524 }, "geometry": { "type": "Point", "coordinates": [ 134.694548200000014, 34.8393524 ] } },
{ "type": "Feature", "properties": { "osm_id": "11388885669", "name": null, "barrier": null, "highway": null, "ref": null, "address": null, "is_in": null, "place": null, "man_made": null, "other_tags": "\"access\"=>\"customers\",\"check_date\"=>\"2023-12-02\",\"defibrillator:location:en\"=>\"Right after main keep entrance\",\"emergency\"=>\"defibrillator\",\"indoor\"=>\"yes\",\"level\"=>\"0\"", "area": null, "centroid_x": 134.6939547, "centroid_y": 34.8393298 }, "geometry": { "type": "Point", "coordinates": [ 134.6939547, 34.8393298 ] } },
{ "type": "Feature", "properties": { "osm_id": "12006244566", "name": null, "barrier": null, "highway": null, "ref": null, "address": null, "is_in": null, "place": null, "man_made": null, "other_tags": "\"amenity\"=>\"smoking_area\"", "area": null, "centroid_x": 134.6924963, "centroid_y": 34.8368008 }, "geometry": { "type": "Point", "coordinates": [ 134.692496299999988, 34.8368008 ] } },
{ "type": "Feature", "properties": { "osm_id": "12368839801", "name": null, "barrier": null, "highway": null, "ref": null, "address": null, "is_in": null, "place": null, "man_made": null, "other_tags": "\"shop\"=>\"ticket\"", "area": null, "centroid_x": 134.6926193, "centroid_y": 34.838278 }, "geometry": { "type": "Point", "coordinates": [ 134.6926193, 34.838278 ] } },
{ "type": "Feature", "properties": { "osm_id": "12615302901", "name": "Western Bailey Corridor", "barrier": null, "highway": null, "ref": null, "address": null, "is_in": null, "place": null, "man_made": null, "other_tags": "\"fee\"=>\"no\",\"tourism\"=>\"museum\"", "area": null, "centroid_x": 134.6913493, "centroid_y": 34.8383107 }, "geometry": { "type": "Point", "coordinates": [ 134.691349300000013, 34.8383107 ] } }
]
}
