{
    "features": [
        {
            "geometry": {
                "coordinates": [
                    [
                        [
                            [
                                139.728512,
                                35.5349879
                            ],
                            [
                                139.729002,
                                35.5349333
                            ],
                            [
                                139.7290202,
                                35.5350858
                            ],
                            [
                                139.730057,
                                35.5349887
                            ],
                            [
                                139.7305007,
                                35.534927
                            ],
                            [
                                139.7302909,
                                35.5340247
                            ],
                            [
                                139.7302015,
                                35.5331
                            ],
                            [
                                139.7298436,
                                35.5330417
                            ],
                            [
                                139.729517,
                                35.533049
                            ],
                            [
                                139.7290518,
                                35.5331
                            ],
                            [
                                139.72877,
                                35.5331437
                            ],
                            [
                                139.728399,
                                35.5348437
                            ],
                            [
                                139.7284291,
                                35.535124
                            ],
                            [
                                139.7284472,
                                35.5351418
                            ],
                            [
                                139.7285242,
                                35.5351323
                            ],
                            [
                                139.728512,
                                35.5349879
                            ]
                        ]
                    ]
                ],
                "type": "MultiPolygon"
            },
            "properties": {
                "id": 0,
                "layer": "XXX",
                "path": "Polygon&uid={e21198ee-acea-4cde-92df-29007c0b4a89}"
            },
            "type": "Feature"
        }
    ],
    "type": "FeatureCollection"
}