{
"type": "FeatureCollection",
"name": "map-midpoints",
"crs": { "type": "name", "properties": { "name": "urn:ogc:def:crs:OGC:1.3:CRS84" } },
"features": [
{ "type": "Feature", "properties": { "osm_id": "209773557", "name": null, "highway": "pedestrian", "waterway": null, "aerialway": null, "barrier": null, "man_made": null, "z_order": 0, "other_tags": null }, "geometry": { "type": "Point", "coordinates": [ 139.488075093969769, 35.348129064650614 ] } },
{ "type": "Feature", "properties": { "osm_id": "209773558", "name": null, "highway": "pedestrian", "waterway": null, "aerialway": null, "barrier": null, "man_made": null, "z_order": 0, "other_tags": null }, "geometry": { "type": "Point", "coordinates": [ 139.488172090824406, 35.347879761451892 ] } },
{ "type": "Feature", "properties": { "osm_id": "210336329", "name": null, "highway": "pedestrian", "waterway": null, "aerialway": null, "barrier": null, "man_made": null, "z_order": 0, "other_tags": "\"access\"=>\"private\"" }, "geometry": { "type": "Point", "coordinates": [ 139.487305848902395, 35.348534155860285 ] } },
{ "type": "Feature", "properties": { "osm_id": "210336330", "name": null, "highway": "pedestrian", "waterway": null, "aerialway": null, "barrier": null, "man_made": null, "z_order": 0, "other_tags": null }, "geometry": { "type": "Point", "coordinates": [ 139.487657150000018, 35.34860365 ] } },
{ "type": "Feature", "properties": { "osm_id": "210337390", "name": "いろは坂", "highway": "pedestrian", "waterway": null, "aerialway": null, "barrier": null, "man_made": null, "z_order": 0, "other_tags": null }, "geometry": { "type": "Point", "coordinates": [ 139.487663631148479, 35.34731014158352 ] } },
{ "type": "Feature", "properties": { "osm_id": "210337568", "name": null, "highway": "footway", "waterway": null, "aerialway": null, "barrier": null, "man_made": null, "z_order": 0, "other_tags": null }, "geometry": { "type": "Point", "coordinates": [ 139.487850049070261, 35.347168335810473 ] } },
{ "type": "Feature", "properties": { "osm_id": "210337569", "name": null, "highway": "pedestrian", "waterway": null, "aerialway": null, "barrier": null, "man_made": null, "z_order": 0, "other_tags": null }, "geometry": { "type": "Point", "coordinates": [ 139.488819281022757, 35.348105593956696 ] } },
{ "type": "Feature", "properties": { "osm_id": "210338092", "name": null, "highway": "pedestrian", "waterway": null, "aerialway": null, "barrier": null, "man_made": null, "z_order": 0, "other_tags": null }, "geometry": { "type": "Point", "coordinates": [ 139.488385944179726, 35.347999638496546 ] } },
{ "type": "Feature", "properties": { "osm_id": "210338093", "name": null, "highway": "pedestrian", "waterway": null, "aerialway": null, "barrier": null, "man_made": null, "z_order": 0, "other_tags": null }, "geometry": { "type": "Point", "coordinates": [ 139.488792836302935, 35.348127210443906 ] } },
{ "type": "Feature", "properties": { "osm_id": "210338094", "name": null, "highway": "pedestrian", "waterway": null, "aerialway": null, "barrier": null, "man_made": null, "z_order": 0, "other_tags": null }, "geometry": { "type": "Point", "coordinates": [ 139.488756151051774, 35.348256910981632 ] } },
{ "type": "Feature", "properties": { "osm_id": "210338095", "name": null, "highway": "pedestrian", "waterway": null, "aerialway": null, "barrier": null, "man_made": null, "z_order": 0, "other_tags": null }, "geometry": { "type": "Point", "coordinates": [ 139.488519621876719, 35.34799015743183 ] } },
{ "type": "Feature", "properties": { "osm_id": "210338139", "name": null, "highway": "service", "waterway": null, "aerialway": null, "barrier": null, "man_made": null, "z_order": 0, "other_tags": null }, "geometry": { "type": "Point", "coordinates": [ 139.488641389027947, 35.347683122099312 ] } },
{ "type": "Feature", "properties": { "osm_id": "210338141", "name": null, "highway": "pedestrian", "waterway": null, "aerialway": null, "barrier": null, "man_made": null, "z_order": 0, "other_tags": null }, "geometry": { "type": "Point", "coordinates": [ 139.48853785, 35.34822555 ] } },
{ "type": "Feature", "properties": { "osm_id": "210339920", "name": null, "highway": "footway", "waterway": null, "aerialway": null, "barrier": null, "man_made": null, "z_order": 0, "other_tags": null }, "geometry": { "type": "Point", "coordinates": [ 139.4874316, 35.34776955 ] } },
{ "type": "Feature", "properties": { "osm_id": "210522627", "name": null, "highway": "steps", "waterway": null, "aerialway": null, "barrier": null, "man_made": null, "z_order": 0, "other_tags": null }, "geometry": { "type": "Point", "coordinates": [ 139.48807265, 35.3471193 ] } },
{ "type": "Feature", "properties": { "osm_id": "210522628", "name": null, "highway": "steps", "waterway": null, "aerialway": null, "barrier": null, "man_made": null, "z_order": 0, "other_tags": null }, "geometry": { "type": "Point", "coordinates": [ 139.4878955, 35.34719135 ] } },
{ "type": "Feature", "properties": { "osm_id": "210522629", "name": null, "highway": "footway", "waterway": null, "aerialway": null, "barrier": null, "man_made": null, "z_order": 20, "other_tags": "\"bridge\"=>\"yes\",\"bridge:name\"=>\"橋本橋\",\"layer\"=>\"1\"" }, "geometry": { "type": "Point", "coordinates": [ 139.4878363, 35.3476124 ] } },
{ "type": "Feature", "properties": { "osm_id": "210522633", "name": null, "highway": "footway", "waterway": null, "aerialway": null, "barrier": null, "man_made": null, "z_order": 0, "other_tags": null }, "geometry": { "type": "Point", "coordinates": [ 139.4878572, 35.3476015 ] } },
{ "type": "Feature", "properties": { "osm_id": "210522634", "name": null, "highway": "footway", "waterway": null, "aerialway": null, "barrier": null, "man_made": null, "z_order": 0, "other_tags": null }, "geometry": { "type": "Point", "coordinates": [ 139.487895854598662, 35.347240628423215 ] } },
{ "type": "Feature", "properties": { "osm_id": "848297642", "name": null, "highway": "footway", "waterway": null, "aerialway": null, "barrier": null, "man_made": null, "z_order": 0, "other_tags": null }, "geometry": { "type": "Point", "coordinates": [ 139.487828209863437, 35.348054037486591 ] } },
{ "type": "Feature", "properties": { "osm_id": "848297645", "name": null, "highway": null, "waterway": null, "aerialway": null, "barrier": "wall", "man_made": null, "z_order": 0, "other_tags": null }, "geometry": { "type": "Point", "coordinates": [ 139.487584484251386, 35.34840460481189 ] } },
{ "type": "Feature", "properties": { "osm_id": "848297646", "name": null, "highway": "footway", "waterway": null, "aerialway": null, "barrier": null, "man_made": null, "z_order": 0, "other_tags": null }, "geometry": { "type": "Point", "coordinates": [ 139.488298217742567, 35.348570482122476 ] } },
{ "type": "Feature", "properties": { "osm_id": "848297651", "name": null, "highway": "footway", "waterway": null, "aerialway": null, "barrier": null, "man_made": null, "z_order": 0, "other_tags": null }, "geometry": { "type": "Point", "coordinates": [ 139.4878208, 35.3484428 ] } },
{ "type": "Feature", "properties": { "osm_id": "848305809", "name": null, "highway": "footway", "waterway": null, "aerialway": null, "barrier": null, "man_made": null, "z_order": 0, "other_tags": null }, "geometry": { "type": "Point", "coordinates": [ 139.488395972109316, 35.349042179803916 ] } },
{ "type": "Feature", "properties": { "osm_id": "848305810", "name": null, "highway": "footway", "waterway": null, "aerialway": null, "barrier": null, "man_made": null, "z_order": 0, "other_tags": null }, "geometry": { "type": "Point", "coordinates": [ 139.488422844970216, 35.349109431988623 ] } },
{ "type": "Feature", "properties": { "osm_id": "848305811", "name": null, "highway": "footway", "waterway": null, "aerialway": null, "barrier": null, "man_made": null, "z_order": 0, "other_tags": null }, "geometry": { "type": "Point", "coordinates": [ 139.488350312006133, 35.34914705203407 ] } },
{ "type": "Feature", "properties": { "osm_id": "848305812", "name": null, "highway": "footway", "waterway": null, "aerialway": null, "barrier": null, "man_made": null, "z_order": 0, "other_tags": null }, "geometry": { "type": "Point", "coordinates": [ 139.488262747990575, 35.34914499783801 ] } },
{ "type": "Feature", "properties": { "osm_id": "848692922", "name": null, "highway": null, "waterway": null, "aerialway": null, "barrier": "city_wall", "man_made": null, "z_order": 0, "other_tags": null }, "geometry": { "type": "Point", "coordinates": [ 139.487477137760351, 35.346912603768835 ] } },
{ "type": "Feature", "properties": { "osm_id": "848692923", "name": null, "highway": null, "waterway": null, "aerialway": null, "barrier": "city_wall", "man_made": null, "z_order": 0, "other_tags": null }, "geometry": { "type": "Point", "coordinates": [ 139.48728436290844, 35.346980025214506 ] } },
{ "type": "Feature", "properties": { "osm_id": "848692926", "name": null, "highway": null, "waterway": null, "aerialway": null, "barrier": "retaining_wall", "man_made": null, "z_order": 0, "other_tags": "\"height\"=>\"1\"" }, "geometry": { "type": "Point", "coordinates": [ 139.48739095000002, 35.34698525 ] } },
{ "type": "Feature", "properties": { "osm_id": "848692927", "name": null, "highway": null, "waterway": null, "aerialway": null, "barrier": "wall", "man_made": null, "z_order": 0, "other_tags": "\"height\"=>\"1\"" }, "geometry": { "type": "Point", "coordinates": [ 139.487776600000018, 35.34718955 ] } },
{ "type": "Feature", "properties": { "osm_id": "848696375", "name": null, "highway": "pedestrian", "waterway": null, "aerialway": null, "barrier": null, "man_made": null, "z_order": 0, "other_tags": null }, "geometry": { "type": "Point", "coordinates": [ 139.488383089025632, 35.348087017757827 ] } },
{ "type": "Feature", "properties": { "osm_id": "848696376", "name": null, "highway": "steps", "waterway": null, "aerialway": null, "barrier": null, "man_made": null, "z_order": 0, "other_tags": null }, "geometry": { "type": "Point", "coordinates": [ 139.48830505, 35.3479945 ] } },
{ "type": "Feature", "properties": { "osm_id": "848696377", "name": null, "highway": "pedestrian", "waterway": null, "aerialway": null, "barrier": null, "man_made": null, "z_order": 0, "other_tags": null }, "geometry": { "type": "Point", "coordinates": [ 139.48846425, 35.34818705 ] } },
{ "type": "Feature", "properties": { "osm_id": "848696378", "name": null, "highway": "steps", "waterway": null, "aerialway": null, "barrier": null, "man_made": null, "z_order": 0, "other_tags": null }, "geometry": { "type": "Point", "coordinates": [ 139.4884586, 35.3481792 ] } },
{ "type": "Feature", "properties": { "osm_id": "848696379", "name": null, "highway": "pedestrian", "waterway": null, "aerialway": null, "barrier": null, "man_made": null, "z_order": 0, "other_tags": null }, "geometry": { "type": "Point", "coordinates": [ 139.48845315, 35.3482315 ] } },
{ "type": "Feature", "properties": { "osm_id": "848696380", "name": null, "highway": "pedestrian", "waterway": null, "aerialway": null, "barrier": null, "man_made": null, "z_order": 0, "other_tags": null }, "geometry": { "type": "Point", "coordinates": [ 139.488488618844315, 35.348194416541112 ] } },
{ "type": "Feature", "properties": { "osm_id": "848696381", "name": null, "highway": "pedestrian", "waterway": null, "aerialway": null, "barrier": null, "man_made": null, "z_order": 0, "other_tags": null }, "geometry": { "type": "Point", "coordinates": [ 139.488521530545682, 35.348257145109407 ] } },
{ "type": "Feature", "properties": { "osm_id": "848696382", "name": null, "highway": "steps", "waterway": null, "aerialway": null, "barrier": null, "man_made": null, "z_order": 0, "other_tags": null }, "geometry": { "type": "Point", "coordinates": [ 139.48847655, 35.348259 ] } },
{ "type": "Feature", "properties": { "osm_id": "848696383", "name": null, "highway": "pedestrian", "waterway": null, "aerialway": null, "barrier": null, "man_made": null, "z_order": 0, "other_tags": null }, "geometry": { "type": "Point", "coordinates": [ 139.488566100000014, 35.3481647 ] } },
{ "type": "Feature", "properties": { "osm_id": "848699567", "name": null, "highway": null, "waterway": null, "aerialway": null, "barrier": "retaining_wall", "man_made": null, "z_order": 0, "other_tags": "\"height\"=>\"0.5\"" }, "geometry": { "type": "Point", "coordinates": [ 139.48839178523906, 35.347959058223488 ] } },
{ "type": "Feature", "properties": { "osm_id": "848699568", "name": null, "highway": null, "waterway": null, "aerialway": null, "barrier": "retaining_wall", "man_made": null, "z_order": 0, "other_tags": "\"height\"=>\"0.5\"" }, "geometry": { "type": "Point", "coordinates": [ 139.488425733151189, 35.34819121530078 ] } },
{ "type": "Feature", "properties": { "osm_id": "848699569", "name": null, "highway": null, "waterway": null, "aerialway": null, "barrier": "retaining_wall", "man_made": null, "z_order": 0, "other_tags": "\"height\"=>\"0.5\"" }, "geometry": { "type": "Point", "coordinates": [ 139.4886167602981, 35.348150775335043 ] } },
{ "type": "Feature", "properties": { "osm_id": "848732149", "name": null, "highway": null, "waterway": null, "aerialway": null, "barrier": "retaining_wall", "man_made": null, "z_order": 0, "other_tags": "\"height\"=>\"0.5\"" }, "geometry": { "type": "Point", "coordinates": [ 139.487686600000018, 35.3472687 ] } },
{ "type": "Feature", "properties": { "osm_id": "848732150", "name": null, "highway": null, "waterway": null, "aerialway": null, "barrier": "retaining_wall", "man_made": null, "z_order": 0, "other_tags": "\"height\"=>\"0.5\"" }, "geometry": { "type": "Point", "coordinates": [ 139.487770599999976, 35.34739815 ] } },
{ "type": "Feature", "properties": { "osm_id": "848732151", "name": null, "highway": null, "waterway": null, "aerialway": null, "barrier": "wall", "man_made": null, "z_order": 0, "other_tags": null }, "geometry": { "type": "Point", "coordinates": [ 139.488148449999983, 35.34744875 ] } },
{ "type": "Feature", "properties": { "osm_id": "848762733", "name": null, "highway": null, "waterway": null, "aerialway": null, "barrier": "fence", "man_made": null, "z_order": 0, "other_tags": null }, "geometry": { "type": "Point", "coordinates": [ 139.487709349999989, 35.3478546 ] } },
{ "type": "Feature", "properties": { "osm_id": "848762734", "name": null, "highway": null, "waterway": null, "aerialway": null, "barrier": "fence", "man_made": null, "z_order": 0, "other_tags": null }, "geometry": { "type": "Point", "coordinates": [ 139.487962087066109, 35.347630198515581 ] } },
{ "type": "Feature", "properties": { "osm_id": "849082181", "name": null, "highway": "footway", "waterway": null, "aerialway": null, "barrier": null, "man_made": null, "z_order": 0, "other_tags": null }, "geometry": { "type": "Point", "coordinates": [ 139.488846958147775, 35.348775385963719 ] } },
{ "type": "Feature", "properties": { "osm_id": "849082182", "name": null, "highway": "footway", "waterway": null, "aerialway": null, "barrier": null, "man_made": null, "z_order": 0, "other_tags": null }, "geometry": { "type": "Point", "coordinates": [ 139.48802705, 35.3483687 ] } },
{ "type": "Feature", "properties": { "osm_id": "849082184", "name": null, "highway": null, "waterway": null, "aerialway": null, "barrier": "retaining_wall", "man_made": null, "z_order": 0, "other_tags": null }, "geometry": { "type": "Point", "coordinates": [ 139.48741644498736, 35.347213445686513 ] } },
{ "type": "Feature", "properties": { "osm_id": "849082185", "name": null, "highway": null, "waterway": null, "aerialway": null, "barrier": "retaining_wall", "man_made": null, "z_order": 0, "other_tags": "\"height\"=>\"4\",\"material\"=>\"concrete\"" }, "geometry": { "type": "Point", "coordinates": [ 139.488850997215479, 35.348610923906989 ] } },
{ "type": "Feature", "properties": { "osm_id": "849082186", "name": null, "highway": null, "waterway": null, "aerialway": null, "barrier": "wall", "man_made": null, "z_order": 0, "other_tags": null }, "geometry": { "type": "Point", "coordinates": [ 139.487537949999989, 35.347759 ] } },
{ "type": "Feature", "properties": { "osm_id": "849082188", "name": null, "highway": "footway", "waterway": null, "aerialway": null, "barrier": null, "man_made": null, "z_order": 0, "other_tags": null }, "geometry": { "type": "Point", "coordinates": [ 139.487900702445131, 35.34723905599855 ] } },
{ "type": "Feature", "properties": { "osm_id": "849082189", "name": null, "highway": null, "waterway": null, "aerialway": null, "barrier": "wall", "man_made": null, "z_order": 0, "other_tags": null }, "geometry": { "type": "Point", "coordinates": [ 139.487639840498531, 35.347744814175613 ] } },
{ "type": "Feature", "properties": { "osm_id": "849082190", "name": null, "highway": "footway", "waterway": null, "aerialway": null, "barrier": null, "man_made": null, "z_order": 0, "other_tags": "\"ford\"=>\"yes\"" }, "geometry": { "type": "Point", "coordinates": [ 139.488216185940615, 35.348495879513514 ] } },
{ "type": "Feature", "properties": { "osm_id": "849082191", "name": null, "highway": "steps", "waterway": null, "aerialway": null, "barrier": null, "man_made": null, "z_order": 0, "other_tags": null }, "geometry": { "type": "Point", "coordinates": [ 139.48907435000001, 35.34846215 ] } },
{ "type": "Feature", "properties": { "osm_id": "849082192", "name": null, "highway": null, "waterway": null, "aerialway": null, "barrier": "hedge", "man_made": null, "z_order": 0, "other_tags": null }, "geometry": { "type": "Point", "coordinates": [ 139.487662067360958, 35.348301446648989 ] } },
{ "type": "Feature", "properties": { "osm_id": "849082193", "name": null, "highway": "footway", "waterway": null, "aerialway": null, "barrier": null, "man_made": null, "z_order": 0, "other_tags": null }, "geometry": { "type": "Point", "coordinates": [ 139.487850084945904, 35.347350743431349 ] } },
{ "type": "Feature", "properties": { "osm_id": "849082194", "name": null, "highway": null, "waterway": null, "aerialway": null, "barrier": "retaining_wall", "man_made": null, "z_order": 0, "other_tags": "\"height\"=>\"1\"" }, "geometry": { "type": "Point", "coordinates": [ 139.48845695, 35.34887965 ] } },
{ "type": "Feature", "properties": { "osm_id": "849082195", "name": null, "highway": "footway", "waterway": null, "aerialway": null, "barrier": null, "man_made": null, "z_order": 0, "other_tags": null }, "geometry": { "type": "Point", "coordinates": [ 139.48870415, 35.34890735 ] } },
{ "type": "Feature", "properties": { "osm_id": "849082196", "name": null, "highway": null, "waterway": null, "aerialway": null, "barrier": "retaining_wall", "man_made": null, "z_order": 0, "other_tags": "\"height\"=>\"2\",\"material\"=>\"concrete\"" }, "geometry": { "type": "Point", "coordinates": [ 139.48942635, 35.34849675 ] } },
{ "type": "Feature", "properties": { "osm_id": "849082197", "name": null, "highway": null, "waterway": null, "aerialway": null, "barrier": "retaining_wall", "man_made": null, "z_order": 0, "other_tags": "\"height\"=>\"1\"" }, "geometry": { "type": "Point", "coordinates": [ 139.488491211558454, 35.349054318181636 ] } },
{ "type": "Feature", "properties": { "osm_id": "849082198", "name": null, "highway": null, "waterway": null, "aerialway": null, "barrier": "hedge", "man_made": null, "z_order": 0, "other_tags": null }, "geometry": { "type": "Point", "coordinates": [ 139.488509779156146, 35.348801282123247 ] } },
{ "type": "Feature", "properties": { "osm_id": "849082199", "name": null, "highway": null, "waterway": null, "aerialway": null, "barrier": "retaining_wall", "man_made": null, "z_order": 0, "other_tags": "\"height\"=>\"2\"" }, "geometry": { "type": "Point", "coordinates": [ 139.489084684258046, 35.348939177545724 ] } },
{ "type": "Feature", "properties": { "osm_id": "849082200", "name": null, "highway": null, "waterway": null, "aerialway": null, "barrier": "wall", "man_made": null, "z_order": 0, "other_tags": null }, "geometry": { "type": "Point", "coordinates": [ 139.488116199999979, 35.34836665 ] } },
{ "type": "Feature", "properties": { "osm_id": "849082201", "name": null, "highway": "steps", "waterway": null, "aerialway": null, "barrier": null, "man_made": null, "z_order": 0, "other_tags": null }, "geometry": { "type": "Point", "coordinates": [ 139.48825435, 35.34816335 ] } },
{ "type": "Feature", "properties": { "osm_id": "849082202", "name": null, "highway": "steps", "waterway": null, "aerialway": null, "barrier": null, "man_made": null, "z_order": 0, "other_tags": null }, "geometry": { "type": "Point", "coordinates": [ 139.48895575, 35.34822065 ] } },
{ "type": "Feature", "properties": { "osm_id": "849082203", "name": null, "highway": null, "waterway": null, "aerialway": null, "barrier": "retaining_wall", "man_made": null, "z_order": 0, "other_tags": "\"height\"=>\"1\"" }, "geometry": { "type": "Point", "coordinates": [ 139.487558040821028, 35.347101049849435 ] } },
{ "type": "Feature", "properties": { "osm_id": "849082204", "name": null, "highway": "steps", "waterway": null, "aerialway": null, "barrier": null, "man_made": null, "z_order": 0, "other_tags": "\"access\"=>\"no\"" }, "geometry": { "type": "Point", "coordinates": [ 139.488393599092717, 35.348813502091879 ] } },
{ "type": "Feature", "properties": { "osm_id": "849082205", "name": null, "highway": "footway", "waterway": null, "aerialway": null, "barrier": null, "man_made": null, "z_order": 0, "other_tags": null }, "geometry": { "type": "Point", "coordinates": [ 139.489159540070489, 35.348676088700898 ] } },
{ "type": "Feature", "properties": { "osm_id": "849082206", "name": null, "highway": "footway", "waterway": null, "aerialway": null, "barrier": null, "man_made": null, "z_order": 0, "other_tags": null }, "geometry": { "type": "Point", "coordinates": [ 139.488586749632674, 35.348841414588406 ] } },
{ "type": "Feature", "properties": { "osm_id": "849082207", "name": null, "highway": null, "waterway": null, "aerialway": null, "barrier": "retaining_wall", "man_made": null, "z_order": 0, "other_tags": "\"height\"=>\"1\",\"material\"=>\"stone\"" }, "geometry": { "type": "Point", "coordinates": [ 139.488493113230192, 35.348086217844127 ] } },
{ "type": "Feature", "properties": { "osm_id": "849082208", "name": null, "highway": "pedestrian", "waterway": null, "aerialway": null, "barrier": null, "man_made": null, "z_order": 0, "other_tags": "\"access\"=>\"no\"" }, "geometry": { "type": "Point", "coordinates": [ 139.487899212479959, 35.348420299436881 ] } },
{ "type": "Feature", "properties": { "osm_id": "849082209", "name": null, "highway": "footway", "waterway": null, "aerialway": null, "barrier": null, "man_made": null, "z_order": 0, "other_tags": null }, "geometry": { "type": "Point", "coordinates": [ 139.48791925, 35.3486463 ] } },
{ "type": "Feature", "properties": { "osm_id": "849082211", "name": null, "highway": "footway", "waterway": null, "aerialway": null, "barrier": null, "man_made": null, "z_order": 0, "other_tags": null }, "geometry": { "type": "Point", "coordinates": [ 139.48896535, 35.34899245 ] } },
{ "type": "Feature", "properties": { "osm_id": "849082212", "name": null, "highway": null, "waterway": null, "aerialway": null, "barrier": "fence", "man_made": null, "z_order": 0, "other_tags": null }, "geometry": { "type": "Point", "coordinates": [ 139.488812849999988, 35.34865965 ] } },
{ "type": "Feature", "properties": { "osm_id": "849082213", "name": null, "highway": null, "waterway": null, "aerialway": null, "barrier": "retaining_wall", "man_made": null, "z_order": 0, "other_tags": "\"height\"=>\"4\",\"material\"=>\"stone\"" }, "geometry": { "type": "Point", "coordinates": [ 139.488259818541849, 35.34740075169767 ] } },
{ "type": "Feature", "properties": { "osm_id": "849082214", "name": null, "highway": null, "waterway": null, "aerialway": null, "barrier": "hedge", "man_made": null, "z_order": 0, "other_tags": null }, "geometry": { "type": "Point", "coordinates": [ 139.487783550000017, 35.347223 ] } },
{ "type": "Feature", "properties": { "osm_id": "849082215", "name": null, "highway": "footway", "waterway": null, "aerialway": null, "barrier": null, "man_made": null, "z_order": 0, "other_tags": null }, "geometry": { "type": "Point", "coordinates": [ 139.488860761893534, 35.348892858501955 ] } },
{ "type": "Feature", "properties": { "osm_id": "849082216", "name": null, "highway": "service", "waterway": null, "aerialway": null, "barrier": null, "man_made": null, "z_order": 0, "other_tags": null }, "geometry": { "type": "Point", "coordinates": [ 139.487866131656745, 35.348187539580401 ] } },
{ "type": "Feature", "properties": { "osm_id": "849082217", "name": null, "highway": "steps", "waterway": null, "aerialway": null, "barrier": null, "man_made": null, "z_order": 0, "other_tags": null }, "geometry": { "type": "Point", "coordinates": [ 139.48848295, 35.34881655 ] } },
{ "type": "Feature", "properties": { "osm_id": "849082220", "name": null, "highway": null, "waterway": null, "aerialway": null, "barrier": "wall", "man_made": null, "z_order": 0, "other_tags": null }, "geometry": { "type": "Point", "coordinates": [ 139.488092699999982, 35.34841475 ] } },
{ "type": "Feature", "properties": { "osm_id": "849082221", "name": null, "highway": null, "waterway": null, "aerialway": null, "barrier": "retaining_wall", "man_made": null, "z_order": 0, "other_tags": "\"height\"=>\"2\"" }, "geometry": { "type": "Point", "coordinates": [ 139.48798284999998, 35.3471531 ] } },
{ "type": "Feature", "properties": { "osm_id": "849082222", "name": null, "highway": "footway", "waterway": null, "aerialway": null, "barrier": null, "man_made": null, "z_order": 0, "other_tags": null }, "geometry": { "type": "Point", "coordinates": [ 139.487881422639333, 35.34855796112609 ] } },
{ "type": "Feature", "properties": { "osm_id": "849082223", "name": null, "highway": "steps", "waterway": null, "aerialway": null, "barrier": null, "man_made": null, "z_order": 0, "other_tags": null }, "geometry": { "type": "Point", "coordinates": [ 139.487534700000026, 35.3477435 ] } },
{ "type": "Feature", "properties": { "osm_id": "849082224", "name": null, "highway": "footway", "waterway": null, "aerialway": null, "barrier": null, "man_made": null, "z_order": 0, "other_tags": "\"ford\"=>\"yes\"" }, "geometry": { "type": "Point", "coordinates": [ 139.48785455, 35.34803 ] } },
{ "type": "Feature", "properties": { "osm_id": "849082225", "name": null, "highway": "footway", "waterway": null, "aerialway": null, "barrier": null, "man_made": null, "z_order": 0, "other_tags": "\"access\"=>\"private\"" }, "geometry": { "type": "Point", "coordinates": [ 139.488321546711319, 35.349349653710767 ] } },
{ "type": "Feature", "properties": { "osm_id": "849082226", "name": null, "highway": "steps", "waterway": null, "aerialway": null, "barrier": null, "man_made": null, "z_order": 0, "other_tags": null }, "geometry": { "type": "Point", "coordinates": [ 139.488930550000021, 35.3488969 ] } },
{ "type": "Feature", "properties": { "osm_id": "849082227", "name": null, "highway": "steps", "waterway": null, "aerialway": null, "barrier": null, "man_made": null, "z_order": 0, "other_tags": null }, "geometry": { "type": "Point", "coordinates": [ 139.48925645, 35.3488634 ] } },
{ "type": "Feature", "properties": { "osm_id": "849082228", "name": null, "highway": null, "waterway": null, "aerialway": null, "barrier": "hedge", "man_made": null, "z_order": 0, "other_tags": null }, "geometry": { "type": "Point", "coordinates": [ 139.487983900000017, 35.34716045 ] } },
{ "type": "Feature", "properties": { "osm_id": "849082229", "name": null, "highway": null, "waterway": null, "aerialway": null, "barrier": "retaining_wall", "man_made": null, "z_order": 0, "other_tags": "\"height\"=>\"4\"" }, "geometry": { "type": "Point", "coordinates": [ 139.487463749999989, 35.3475586 ] } },
{ "type": "Feature", "properties": { "osm_id": "849082230", "name": null, "highway": null, "waterway": null, "aerialway": null, "barrier": "retaining_wall", "man_made": null, "z_order": 0, "other_tags": "\"height\"=>\"0.5\"" }, "geometry": { "type": "Point", "coordinates": [ 139.48774597161551, 35.348559584014552 ] } },
{ "type": "Feature", "properties": { "osm_id": "849082231", "name": null, "highway": "steps", "waterway": null, "aerialway": null, "barrier": null, "man_made": null, "z_order": 0, "other_tags": null }, "geometry": { "type": "Point", "coordinates": [ 139.4887316, 35.34895165 ] } },
{ "type": "Feature", "properties": { "osm_id": "849082232", "name": null, "highway": "service", "waterway": null, "aerialway": null, "barrier": null, "man_made": null, "z_order": 0, "other_tags": null }, "geometry": { "type": "Point", "coordinates": [ 139.488250098797124, 35.347702658856782 ] } },
{ "type": "Feature", "properties": { "osm_id": "849082233", "name": null, "highway": null, "waterway": null, "aerialway": null, "barrier": "hedge", "man_made": null, "z_order": 0, "other_tags": null }, "geometry": { "type": "Point", "coordinates": [ 139.487875240681717, 35.347768593681195 ] } },
{ "type": "Feature", "properties": { "osm_id": "849082234", "name": null, "highway": null, "waterway": null, "aerialway": null, "barrier": "hedge", "man_made": null, "z_order": 0, "other_tags": null }, "geometry": { "type": "Point", "coordinates": [ 139.487916182337443, 35.348020764576603 ] } },
{ "type": "Feature", "properties": { "osm_id": "849082235", "name": null, "highway": "footway", "waterway": null, "aerialway": null, "barrier": null, "man_made": null, "z_order": 0, "other_tags": null }, "geometry": { "type": "Point", "coordinates": [ 139.488213386306825, 35.34756935327438 ] } },
{ "type": "Feature", "properties": { "osm_id": "849082236", "name": null, "highway": null, "waterway": "ditch", "aerialway": null, "barrier": null, "man_made": null, "z_order": 0, "other_tags": null }, "geometry": { "type": "Point", "coordinates": [ 139.487837236548643, 35.347599904909636 ] } },
{ "type": "Feature", "properties": { "osm_id": "849082237", "name": null, "highway": null, "waterway": null, "aerialway": null, "barrier": "retaining_wall", "man_made": null, "z_order": 0, "other_tags": "\"height\"=>\"1\"" }, "geometry": { "type": "Point", "coordinates": [ 139.48777795, 35.34721895 ] } },
{ "type": "Feature", "properties": { "osm_id": "849082239", "name": null, "highway": null, "waterway": null, "aerialway": null, "barrier": "fence", "man_made": null, "z_order": 0, "other_tags": null }, "geometry": { "type": "Point", "coordinates": [ 139.488878908844868, 35.348384565675481 ] } },
{ "type": "Feature", "properties": { "osm_id": "849082240", "name": null, "highway": null, "waterway": null, "aerialway": null, "barrier": "retaining_wall", "man_made": null, "z_order": 0, "other_tags": "\"height\"=>\"3\"" }, "geometry": { "type": "Point", "coordinates": [ 139.489031786928876, 35.348837023993489 ] } },
{ "type": "Feature", "properties": { "osm_id": "849082241", "name": null, "highway": null, "waterway": null, "aerialway": null, "barrier": "wall", "man_made": null, "z_order": 0, "other_tags": null }, "geometry": { "type": "Point", "coordinates": [ 139.487610471174264, 35.347684390735161 ] } },
{ "type": "Feature", "properties": { "osm_id": "849082242", "name": null, "highway": "footway", "waterway": null, "aerialway": null, "barrier": null, "man_made": null, "z_order": 0, "other_tags": "\"ford\"=>\"yes\"" }, "geometry": { "type": "Point", "coordinates": [ 139.488153014861467, 35.348489066793839 ] } },
{ "type": "Feature", "properties": { "osm_id": "849082243", "name": null, "highway": "footway", "waterway": null, "aerialway": null, "barrier": null, "man_made": null, "z_order": 0, "other_tags": null }, "geometry": { "type": "Point", "coordinates": [ 139.488843016096297, 35.348853187639769 ] } },
{ "type": "Feature", "properties": { "osm_id": "849082244", "name": null, "highway": "footway", "waterway": null, "aerialway": null, "barrier": null, "man_made": null, "z_order": 0, "other_tags": null }, "geometry": { "type": "Point", "coordinates": [ 139.488084749999985, 35.34830005 ] } },
{ "type": "Feature", "properties": { "osm_id": "849082245", "name": null, "highway": null, "waterway": null, "aerialway": null, "barrier": "retaining_wall", "man_made": null, "z_order": 0, "other_tags": "\"height\"=>\"3\"" }, "geometry": { "type": "Point", "coordinates": [ 139.487674449999986, 35.3478508 ] } },
{ "type": "Feature", "properties": { "osm_id": "849082246", "name": null, "highway": "steps", "waterway": null, "aerialway": null, "barrier": null, "man_made": null, "z_order": 0, "other_tags": "\"access\"=>\"no\"" }, "geometry": { "type": "Point", "coordinates": [ 139.48838705, 35.34901655 ] } },
{ "type": "Feature", "properties": { "osm_id": "849082247", "name": null, "highway": null, "waterway": null, "aerialway": null, "barrier": "fence", "man_made": null, "z_order": 0, "other_tags": null }, "geometry": { "type": "Point", "coordinates": [ 139.48887935, 35.3482634 ] } },
{ "type": "Feature", "properties": { "osm_id": "849082248", "name": null, "highway": null, "waterway": "ditch", "aerialway": null, "barrier": null, "man_made": null, "z_order": 0, "other_tags": null }, "geometry": { "type": "Point", "coordinates": [ 139.48797865421821, 35.348390000712207 ] } },
{ "type": "Feature", "properties": { "osm_id": "849082249", "name": null, "highway": "steps", "waterway": null, "aerialway": null, "barrier": null, "man_made": null, "z_order": 0, "other_tags": null }, "geometry": { "type": "Point", "coordinates": [ 139.488497600000017, 35.34895975 ] } },
{ "type": "Feature", "properties": { "osm_id": "849082250", "name": null, "highway": null, "waterway": null, "aerialway": null, "barrier": "wall", "man_made": null, "z_order": 0, "other_tags": null }, "geometry": { "type": "Point", "coordinates": [ 139.487846400000024, 35.3476769 ] } },
{ "type": "Feature", "properties": { "osm_id": "849082251", "name": null, "highway": "footway", "waterway": null, "aerialway": null, "barrier": null, "man_made": null, "z_order": 0, "other_tags": null }, "geometry": { "type": "Point", "coordinates": [ 139.488693784730771, 35.348803630815453 ] } },
{ "type": "Feature", "properties": { "osm_id": "849082252", "name": null, "highway": null, "waterway": null, "aerialway": null, "barrier": "retaining_wall", "man_made": null, "z_order": 0, "other_tags": "\"height\"=>\"1\",\"material\"=>\"stone\"" }, "geometry": { "type": "Point", "coordinates": [ 139.4890264, 35.3483666 ] } },
{ "type": "Feature", "properties": { "osm_id": "849082253", "name": null, "highway": null, "waterway": null, "aerialway": null, "barrier": "retaining_wall", "man_made": null, "z_order": 0, "other_tags": "\"height\"=>\"2\",\"material\"=>\"stone\"" }, "geometry": { "type": "Point", "coordinates": [ 139.488869414135024, 35.347816850839031 ] } },
{ "type": "Feature", "properties": { "osm_id": "849082254", "name": null, "highway": null, "waterway": null, "aerialway": null, "barrier": "hedge", "man_made": null, "z_order": 0, "other_tags": null }, "geometry": { "type": "Point", "coordinates": [ 139.488420520590068, 35.348949779734596 ] } },
{ "type": "Feature", "properties": { "osm_id": "849082255", "name": null, "highway": null, "waterway": null, "aerialway": null, "barrier": "hedge", "man_made": null, "z_order": 0, "other_tags": null }, "geometry": { "type": "Point", "coordinates": [ 139.489206449999983, 35.34889235 ] } },
{ "type": "Feature", "properties": { "osm_id": "849082256", "name": null, "highway": null, "waterway": null, "aerialway": null, "barrier": "hedge", "man_made": null, "z_order": 0, "other_tags": null }, "geometry": { "type": "Point", "coordinates": [ 139.488925693396226, 35.348260683987711 ] } },
{ "type": "Feature", "properties": { "osm_id": "849082257", "name": null, "highway": "footway", "waterway": null, "aerialway": null, "barrier": null, "man_made": null, "z_order": 0, "other_tags": null }, "geometry": { "type": "Point", "coordinates": [ 139.488607808613807, 35.347792660950972 ] } },
{ "type": "Feature", "properties": { "osm_id": "849082261", "name": null, "highway": "steps", "waterway": null, "aerialway": null, "barrier": null, "man_made": null, "z_order": 0, "other_tags": null }, "geometry": { "type": "Point", "coordinates": [ 139.4889875, 35.34828505 ] } },
{ "type": "Feature", "properties": { "osm_id": "849082262", "name": null, "highway": null, "waterway": null, "aerialway": null, "barrier": "fence", "man_made": null, "z_order": 0, "other_tags": "\"fence_type\"=>\"wood\"" }, "geometry": { "type": "Point", "coordinates": [ 139.487906220951714, 35.347987586782779 ] } },
{ "type": "Feature", "properties": { "osm_id": "849082263", "name": null, "highway": null, "waterway": null, "aerialway": null, "barrier": "retaining_wall", "man_made": null, "z_order": 0, "other_tags": "\"height\"=>\"1\",\"material\"=>\"stone\"" }, "geometry": { "type": "Point", "coordinates": [ 139.4888846, 35.34818775 ] } },
{ "type": "Feature", "properties": { "osm_id": "849082264", "name": null, "highway": "steps", "waterway": null, "aerialway": null, "barrier": null, "man_made": null, "z_order": 0, "other_tags": null }, "geometry": { "type": "Point", "coordinates": [ 139.488467087799563, 35.348094935249563 ] } },
{ "type": "Feature", "properties": { "osm_id": "849082265", "name": null, "highway": "footway", "waterway": null, "aerialway": null, "barrier": null, "man_made": null, "z_order": 0, "other_tags": null }, "geometry": { "type": "Point", "coordinates": [ 139.487704346175889, 35.347675387614586 ] } },
{ "type": "Feature", "properties": { "osm_id": "849082266", "name": null, "highway": "footway", "waterway": null, "aerialway": null, "barrier": null, "man_made": null, "z_order": 0, "other_tags": null }, "geometry": { "type": "Point", "coordinates": [ 139.488816250000013, 35.3487732 ] } },
{ "type": "Feature", "properties": { "osm_id": "849082267", "name": null, "highway": null, "waterway": null, "aerialway": null, "barrier": "retaining_wall", "man_made": null, "z_order": 0, "other_tags": "\"height\"=>\"1\"" }, "geometry": { "type": "Point", "coordinates": [ 139.48760515, 35.3473005 ] } },
{ "type": "Feature", "properties": { "osm_id": "849082268", "name": null, "highway": null, "waterway": null, "aerialway": null, "barrier": "retaining_wall", "man_made": null, "z_order": 0, "other_tags": "\"height\"=>\"2\"" }, "geometry": { "type": "Point", "coordinates": [ 139.4886692, 35.34764375 ] } },
{ "type": "Feature", "properties": { "osm_id": "849082269", "name": null, "highway": "footway", "waterway": null, "aerialway": null, "barrier": null, "man_made": null, "z_order": 0, "other_tags": null }, "geometry": { "type": "Point", "coordinates": [ 139.48791165, 35.3472187 ] } },
{ "type": "Feature", "properties": { "osm_id": "849082270", "name": null, "highway": null, "waterway": null, "aerialway": null, "barrier": "wall", "man_made": null, "z_order": 0, "other_tags": null }, "geometry": { "type": "Point", "coordinates": [ 139.487908579475999, 35.347571835656673 ] } },
{ "type": "Feature", "properties": { "osm_id": "849082271", "name": null, "highway": "footway", "waterway": null, "aerialway": null, "barrier": null, "man_made": null, "z_order": 0, "other_tags": "\"ford\"=>\"yes\"" }, "geometry": { "type": "Point", "coordinates": [ 139.487905500000011, 35.3485013 ] } },
{ "type": "Feature", "properties": { "osm_id": "849082273", "name": null, "highway": "footway", "waterway": null, "aerialway": null, "barrier": null, "man_made": null, "z_order": 0, "other_tags": null }, "geometry": { "type": "Point", "coordinates": [ 139.489316485046089, 35.348966590926523 ] } },
{ "type": "Feature", "properties": { "osm_id": "849082274", "name": null, "highway": null, "waterway": null, "aerialway": null, "barrier": "retaining_wall", "man_made": null, "z_order": 0, "other_tags": "\"height\"=>\"1\"" }, "geometry": { "type": "Point", "coordinates": [ 139.488206120335803, 35.348203602141481 ] } },
{ "type": "Feature", "properties": { "osm_id": "849082275", "name": null, "highway": "footway", "waterway": null, "aerialway": null, "barrier": null, "man_made": null, "z_order": 0, "other_tags": "\"ford\"=>\"yes\"" }, "geometry": { "type": "Point", "coordinates": [ 139.488271403854213, 35.348520563545662 ] } },
{ "type": "Feature", "properties": { "osm_id": "849082276", "name": null, "highway": "steps", "waterway": null, "aerialway": null, "barrier": null, "man_made": null, "z_order": 0, "other_tags": null }, "geometry": { "type": "Point", "coordinates": [ 139.488891099999989, 35.3481121 ] } },
{ "type": "Feature", "properties": { "osm_id": "849082277", "name": null, "highway": null, "waterway": null, "aerialway": null, "barrier": "hedge", "man_made": null, "z_order": 0, "other_tags": null }, "geometry": { "type": "Point", "coordinates": [ 139.488355300000023, 35.34917685 ] } },
{ "type": "Feature", "properties": { "osm_id": "849082278", "name": null, "highway": null, "waterway": null, "aerialway": null, "barrier": "hedge", "man_made": null, "z_order": 0, "other_tags": null }, "geometry": { "type": "Point", "coordinates": [ 139.487844513818061, 35.348596468531525 ] } },
{ "type": "Feature", "properties": { "osm_id": "849082279", "name": null, "highway": "steps", "waterway": null, "aerialway": null, "barrier": null, "man_made": null, "z_order": 0, "other_tags": null }, "geometry": { "type": "Point", "coordinates": [ 139.48856834999998, 35.34774115 ] } },
{ "type": "Feature", "properties": { "osm_id": "849082280", "name": null, "highway": null, "waterway": null, "aerialway": null, "barrier": "retaining_wall", "man_made": null, "z_order": 0, "other_tags": "\"height\"=>\"1\"" }, "geometry": { "type": "Point", "coordinates": [ 139.488213856194108, 35.348318735786954 ] } },
{ "type": "Feature", "properties": { "osm_id": "849082281", "name": null, "highway": "steps", "waterway": null, "aerialway": null, "barrier": null, "man_made": null, "z_order": 0, "other_tags": null }, "geometry": { "type": "Point", "coordinates": [ 139.4890131, 35.3483371 ] } },
{ "type": "Feature", "properties": { "osm_id": "849082282", "name": null, "highway": "footway", "waterway": null, "aerialway": null, "barrier": null, "man_made": null, "z_order": 0, "other_tags": null }, "geometry": { "type": "Point", "coordinates": [ 139.489429649999977, 35.34886485 ] } },
{ "type": "Feature", "properties": { "osm_id": "849082283", "name": null, "highway": null, "waterway": null, "aerialway": null, "barrier": "retaining_wall", "man_made": null, "z_order": 0, "other_tags": "\"height\"=>\"1\",\"material\"=>\"stone\"" }, "geometry": { "type": "Point", "coordinates": [ 139.48865594802723, 35.348064908309077 ] } },
{ "type": "Feature", "properties": { "osm_id": "849082284", "name": null, "highway": "footway", "waterway": null, "aerialway": null, "barrier": null, "man_made": null, "z_order": 0, "other_tags": "\"access\"=>\"private\"" }, "geometry": { "type": "Point", "coordinates": [ 139.487818752913512, 35.349256473161276 ] } },
{ "type": "Feature", "properties": { "osm_id": "849082285", "name": null, "highway": null, "waterway": null, "aerialway": null, "barrier": "retaining_wall", "man_made": null, "z_order": 0, "other_tags": "\"height\"=>\"2\",\"material\"=>\"stone\"" }, "geometry": { "type": "Point", "coordinates": [ 139.488965650000011, 35.3483572 ] } },
{ "type": "Feature", "properties": { "osm_id": "849082286", "name": null, "highway": null, "waterway": null, "aerialway": null, "barrier": "hedge", "man_made": null, "z_order": 0, "other_tags": null }, "geometry": { "type": "Point", "coordinates": [ 139.488080085069925, 35.348456823379003 ] } },
{ "type": "Feature", "properties": { "osm_id": "849082287", "name": null, "highway": null, "waterway": null, "aerialway": null, "barrier": "wall", "man_made": null, "z_order": 0, "other_tags": null }, "geometry": { "type": "Point", "coordinates": [ 139.4875245, 35.3477294 ] } },
{ "type": "Feature", "properties": { "osm_id": "849082288", "name": null, "highway": "footway", "waterway": null, "aerialway": null, "barrier": null, "man_made": null, "z_order": 0, "other_tags": null }, "geometry": { "type": "Point", "coordinates": [ 139.487356313790798, 35.347014073204996 ] } },
{ "type": "Feature", "properties": { "osm_id": "849082289", "name": null, "highway": null, "waterway": null, "aerialway": null, "barrier": "retaining_wall", "man_made": null, "z_order": 0, "other_tags": "\"height\"=>\"1\"" }, "geometry": { "type": "Point", "coordinates": [ 139.488293279870561, 35.34840592653255 ] } },
{ "type": "Feature", "properties": { "osm_id": "849082290", "name": null, "highway": "footway", "waterway": null, "aerialway": null, "barrier": null, "man_made": null, "z_order": 0, "other_tags": null }, "geometry": { "type": "Point", "coordinates": [ 139.4879225, 35.3472366 ] } },
{ "type": "Feature", "properties": { "osm_id": "849082291", "name": null, "highway": null, "waterway": null, "aerialway": null, "barrier": "retaining_wall", "man_made": null, "z_order": 0, "other_tags": "\"height\"=>\"2\"" }, "geometry": { "type": "Point", "coordinates": [ 139.487605, 35.3473988 ] } },
{ "type": "Feature", "properties": { "osm_id": "849082292", "name": null, "highway": null, "waterway": null, "aerialway": null, "barrier": "retaining_wall", "man_made": null, "z_order": 0, "other_tags": "\"height\"=>\"1\",\"material\"=>\"stone\"" }, "geometry": { "type": "Point", "coordinates": [ 139.489046700000017, 35.3484956 ] } },
{ "type": "Feature", "properties": { "osm_id": "849082293", "name": null, "highway": null, "waterway": null, "aerialway": null, "barrier": "retaining_wall", "man_made": null, "z_order": 0, "other_tags": "\"height\"=>\"3\"" }, "geometry": { "type": "Point", "coordinates": [ 139.488424139513228, 35.347310915145343 ] } },
{ "type": "Feature", "properties": { "osm_id": "849082294", "name": null, "highway": null, "waterway": null, "aerialway": null, "barrier": "hedge", "man_made": null, "z_order": 0, "other_tags": null }, "geometry": { "type": "Point", "coordinates": [ 139.48758885, 35.3482197 ] } },
{ "type": "Feature", "properties": { "osm_id": "849082295", "name": null, "highway": "footway", "waterway": null, "aerialway": null, "barrier": null, "man_made": null, "z_order": 0, "other_tags": null }, "geometry": { "type": "Point", "coordinates": [ 139.48818545, 35.3475511 ] } },
{ "type": "Feature", "properties": { "osm_id": "849082296", "name": null, "highway": "footway", "waterway": null, "aerialway": null, "barrier": null, "man_made": null, "z_order": 0, "other_tags": "\"ford\"=>\"yes\"" }, "geometry": { "type": "Point", "coordinates": [ 139.488234519780804, 35.34845813626756 ] } },
{ "type": "Feature", "properties": { "osm_id": "849082297", "name": null, "highway": null, "waterway": null, "aerialway": null, "barrier": "wall", "man_made": null, "z_order": 0, "other_tags": null }, "geometry": { "type": "Point", "coordinates": [ 139.488752905691541, 35.349006298208991 ] } },
{ "type": "Feature", "properties": { "osm_id": "849082298", "name": null, "highway": null, "waterway": null, "aerialway": null, "barrier": "hedge", "man_made": null, "z_order": 0, "other_tags": null }, "geometry": { "type": "Point", "coordinates": [ 139.487971987722801, 35.347621373845087 ] } },
{ "type": "Feature", "properties": { "osm_id": "849082299", "name": null, "highway": "steps", "waterway": null, "aerialway": null, "barrier": null, "man_made": null, "z_order": 0, "other_tags": null }, "geometry": { "type": "Point", "coordinates": [ 139.489037450000012, 35.3483865 ] } },
{ "type": "Feature", "properties": { "osm_id": "849082300", "name": null, "highway": "steps", "waterway": null, "aerialway": null, "barrier": null, "man_made": null, "z_order": 0, "other_tags": null }, "geometry": { "type": "Point", "coordinates": [ 139.489621549999981, 35.3487938 ] } },
{ "type": "Feature", "properties": { "osm_id": "849082301", "name": null, "highway": "footway", "waterway": null, "aerialway": null, "barrier": null, "man_made": null, "z_order": 0, "other_tags": "\"access\"=>\"no\"" }, "geometry": { "type": "Point", "coordinates": [ 139.488326972427899, 35.348823997110983 ] } },
{ "type": "Feature", "properties": { "osm_id": "849111645", "name": null, "highway": "footway", "waterway": null, "aerialway": null, "barrier": null, "man_made": null, "z_order": 0, "other_tags": null }, "geometry": { "type": "Point", "coordinates": [ 139.488365593036178, 35.348233516107854 ] } },
{ "type": "Feature", "properties": { "osm_id": "849111646", "name": null, "highway": "footway", "waterway": null, "aerialway": null, "barrier": null, "man_made": null, "z_order": 0, "other_tags": null }, "geometry": { "type": "Point", "coordinates": [ 139.488373811785749, 35.348294283604893 ] } },
{ "type": "Feature", "properties": { "osm_id": "849111647", "name": null, "highway": "steps", "waterway": null, "aerialway": null, "barrier": null, "man_made": null, "z_order": 0, "other_tags": null }, "geometry": { "type": "Point", "coordinates": [ 139.488190740843436, 35.348274869110192 ] } },
{ "type": "Feature", "properties": { "osm_id": "849111648", "name": null, "highway": "footway", "waterway": null, "aerialway": null, "barrier": null, "man_made": null, "z_order": 20, "other_tags": "\"bridge\"=>\"yes\",\"layer\"=>\"1\"" }, "geometry": { "type": "Point", "coordinates": [ 139.48805065, 35.348527 ] } },
{ "type": "Feature", "properties": { "osm_id": "849111649", "name": null, "highway": "footway", "waterway": null, "aerialway": null, "barrier": null, "man_made": null, "z_order": 0, "other_tags": "\"ford\"=>\"yes\"" }, "geometry": { "type": "Point", "coordinates": [ 139.487939195753682, 35.348608101857856 ] } },
{ "type": "Feature", "properties": { "osm_id": "849111650", "name": null, "highway": null, "waterway": null, "aerialway": null, "barrier": "fence", "man_made": null, "z_order": 0, "other_tags": "\"fence_type\"=>\"wood\"" }, "geometry": { "type": "Point", "coordinates": [ 139.487970119049351, 35.34865025669211 ] } },
{ "type": "Feature", "properties": { "osm_id": "849111651", "name": null, "highway": null, "waterway": "ditch", "aerialway": null, "barrier": null, "man_made": null, "z_order": 0, "other_tags": null }, "geometry": { "type": "Point", "coordinates": [ 139.487767350000013, 35.3483237 ] } },
{ "type": "Feature", "properties": { "osm_id": "849111652", "name": null, "highway": null, "waterway": "ditch", "aerialway": null, "barrier": null, "man_made": null, "z_order": -10, "other_tags": "\"layer\"=>\"-1\",\"tunnel\"=>\"culvert\"" }, "geometry": { "type": "Point", "coordinates": [ 139.48781655, 35.3483381 ] } },
{ "type": "Feature", "properties": { "osm_id": "849111653", "name": null, "highway": "service", "waterway": null, "aerialway": null, "barrier": null, "man_made": null, "z_order": 0, "other_tags": null }, "geometry": { "type": "Point", "coordinates": [ 139.488403049999988, 35.34768925 ] } },
{ "type": "Feature", "properties": { "osm_id": "849113299", "name": null, "highway": "pedestrian", "waterway": null, "aerialway": null, "barrier": null, "man_made": null, "z_order": 0, "other_tags": null }, "geometry": { "type": "Point", "coordinates": [ 139.487767841759478, 35.348142257776914 ] } },
{ "type": "Feature", "properties": { "osm_id": "849113300", "name": null, "highway": "footway", "waterway": null, "aerialway": null, "barrier": null, "man_made": null, "z_order": 0, "other_tags": null }, "geometry": { "type": "Point", "coordinates": [ 139.488461365897848, 35.34919083586442 ] } },
{ "type": "Feature", "properties": { "osm_id": "849119157", "name": null, "highway": "pedestrian", "waterway": null, "aerialway": null, "barrier": null, "man_made": null, "z_order": 0, "other_tags": null }, "geometry": { "type": "Point", "coordinates": [ 139.487823971510181, 35.348560289234513 ] } },
{ "type": "Feature", "properties": { "osm_id": "849119158", "name": null, "highway": "footway", "waterway": null, "aerialway": null, "barrier": null, "man_made": null, "z_order": 0, "other_tags": null }, "geometry": { "type": "Point", "coordinates": [ 139.4887687, 35.3487459 ] } },
{ "type": "Feature", "properties": { "osm_id": "849119159", "name": null, "highway": null, "waterway": null, "aerialway": null, "barrier": "retaining_wall", "man_made": null, "z_order": 0, "other_tags": "\"height\"=>\"0.5\",\"material\"=>\"stone\"" }, "geometry": { "type": "Point", "coordinates": [ 139.48876775, 35.34910275 ] } },
{ "type": "Feature", "properties": { "osm_id": "849119160", "name": null, "highway": null, "waterway": null, "aerialway": null, "barrier": "hedge", "man_made": null, "z_order": 0, "other_tags": null }, "geometry": { "type": "Point", "coordinates": [ 139.488192234993249, 35.348665225901151 ] } },
{ "type": "Feature", "properties": { "osm_id": "849119161", "name": null, "highway": "pedestrian", "waterway": null, "aerialway": null, "barrier": null, "man_made": null, "z_order": 20, "other_tags": "\"bridge\"=>\"yes\",\"layer\"=>\"1\"" }, "geometry": { "type": "Point", "coordinates": [ 139.487927800000023, 35.3483717 ] } },
{ "type": "Feature", "properties": { "osm_id": "849187120", "name": null, "highway": "footway", "waterway": null, "aerialway": null, "barrier": null, "man_made": null, "z_order": 0, "other_tags": "\"ford\"=>\"yes\"" }, "geometry": { "type": "Point", "coordinates": [ 139.488153852164999, 35.348404534311186 ] } },
{ "type": "Feature", "properties": { "osm_id": "849379671", "name": null, "highway": "footway", "waterway": null, "aerialway": null, "barrier": null, "man_made": null, "z_order": 0, "other_tags": null }, "geometry": { "type": "Point", "coordinates": [ 139.4884932, 35.34782615 ] } },
{ "type": "Feature", "properties": { "osm_id": "849838225", "name": null, "highway": "steps", "waterway": null, "aerialway": null, "barrier": null, "man_made": null, "z_order": 0, "other_tags": null }, "geometry": { "type": "Point", "coordinates": [ 139.488528299999984, 35.3482668 ] } },
{ "type": "Feature", "properties": { "osm_id": "849838226", "name": null, "highway": "footway", "waterway": null, "aerialway": null, "barrier": null, "man_made": null, "z_order": 0, "other_tags": null }, "geometry": { "type": "Point", "coordinates": [ 139.48813795, 35.3476877 ] } },
{ "type": "Feature", "properties": { "osm_id": "850049887", "name": null, "highway": null, "waterway": null, "aerialway": null, "barrier": "hedge", "man_made": null, "z_order": 0, "other_tags": null }, "geometry": { "type": "Point", "coordinates": [ 139.489017620169676, 35.34898074879586 ] } },
{ "type": "Feature", "properties": { "osm_id": "850049890", "name": null, "highway": "footway", "waterway": null, "aerialway": null, "barrier": null, "man_made": null, "z_order": 0, "other_tags": null }, "geometry": { "type": "Point", "coordinates": [ 139.489158560987192, 35.348921724541825 ] } },
{ "type": "Feature", "properties": { "osm_id": "850049891", "name": null, "highway": "footway", "waterway": null, "aerialway": null, "barrier": null, "man_made": null, "z_order": 0, "other_tags": null }, "geometry": { "type": "Point", "coordinates": [ 139.489279399999987, 35.3489465 ] } },
{ "type": "Feature", "properties": { "osm_id": "850355491", "name": null, "highway": null, "waterway": null, "aerialway": null, "barrier": "wall", "man_made": null, "z_order": 0, "other_tags": null }, "geometry": { "type": "Point", "coordinates": [ 139.487946508541683, 35.348400230895315 ] } },
{ "type": "Feature", "properties": { "osm_id": "855281270", "name": null, "highway": null, "waterway": null, "aerialway": null, "barrier": "fence", "man_made": null, "z_order": 0, "other_tags": null }, "geometry": { "type": "Point", "coordinates": [ 139.489145838394535, 35.34911686115899 ] } },
{ "type": "Feature", "properties": { "osm_id": "855281271", "name": null, "highway": "footway", "waterway": null, "aerialway": null, "barrier": null, "man_made": null, "z_order": 0, "other_tags": null }, "geometry": { "type": "Point", "coordinates": [ 139.48916745, 35.3489278 ] } },
{ "type": "Feature", "properties": { "osm_id": "855281273", "name": null, "highway": "footway", "waterway": null, "aerialway": null, "barrier": null, "man_made": null, "z_order": 0, "other_tags": null }, "geometry": { "type": "Point", "coordinates": [ 139.489151159194876, 35.349022147236226 ] } },
{ "type": "Feature", "properties": { "osm_id": "855281274", "name": null, "highway": "footway", "waterway": null, "aerialway": null, "barrier": null, "man_made": null, "z_order": 0, "other_tags": null }, "geometry": { "type": "Point", "coordinates": [ 139.489047394768079, 35.348998885888747 ] } },
{ "type": "Feature", "properties": { "osm_id": "855281276", "name": null, "highway": null, "waterway": null, "aerialway": null, "barrier": "fence", "man_made": null, "z_order": 0, "other_tags": null }, "geometry": { "type": "Point", "coordinates": [ 139.48906701593566, 35.349049714284519 ] } },
{ "type": "Feature", "properties": { "osm_id": "855281277", "name": null, "highway": null, "waterway": null, "aerialway": null, "barrier": "wall", "man_made": null, "z_order": 0, "other_tags": null }, "geometry": { "type": "Point", "coordinates": [ 139.48943540867657, 35.348955957044765 ] } },
{ "type": "Feature", "properties": { "osm_id": "855939293", "name": null, "highway": null, "waterway": null, "aerialway": null, "barrier": "fence", "man_made": null, "z_order": 0, "other_tags": null }, "geometry": { "type": "Point", "coordinates": [ 139.489086900000018, 35.3489617 ] } },
{ "type": "Feature", "properties": { "osm_id": "855939294", "name": null, "highway": "footway", "waterway": null, "aerialway": null, "barrier": null, "man_made": null, "z_order": 0, "other_tags": null }, "geometry": { "type": "Point", "coordinates": [ 139.489138200000014, 35.3490862 ] } },
{ "type": "Feature", "properties": { "osm_id": "879135251", "name": null, "highway": null, "waterway": null, "aerialway": null, "barrier": "fence", "man_made": null, "z_order": 0, "other_tags": null }, "geometry": { "type": "Point", "coordinates": [ 139.489068325758097, 35.349073766187296 ] } },
{ "type": "Feature", "properties": { "osm_id": "879135252", "name": null, "highway": null, "waterway": null, "aerialway": null, "barrier": "fence", "man_made": null, "z_order": 0, "other_tags": null }, "geometry": { "type": "Point", "coordinates": [ 139.489177250000012, 35.34906005 ] } },
{ "type": "Feature", "properties": { "osm_id": "879135254", "name": null, "highway": "footway", "waterway": null, "aerialway": null, "barrier": null, "man_made": null, "z_order": 0, "other_tags": null }, "geometry": { "type": "Point", "coordinates": [ 139.489180949856689, 35.349119729490944 ] } },
{ "type": "Feature", "properties": { "osm_id": "879135257", "name": null, "highway": "footway", "waterway": null, "aerialway": null, "barrier": null, "man_made": null, "z_order": 0, "other_tags": null }, "geometry": { "type": "Point", "coordinates": [ 139.48906782579931, 35.349095017986954 ] } },
{ "type": "Feature", "properties": { "osm_id": "879135258", "name": null, "highway": null, "waterway": null, "aerialway": null, "barrier": "hedge", "man_made": null, "z_order": 0, "other_tags": null }, "geometry": { "type": "Point", "coordinates": [ 139.489068700000018, 35.3490193 ] } },
{ "type": "Feature", "properties": { "osm_id": "879135260", "name": null, "highway": null, "waterway": null, "aerialway": null, "barrier": "retaining_wall", "man_made": null, "z_order": 0, "other_tags": "\"height\"=>\"1\"" }, "geometry": { "type": "Point", "coordinates": [ 139.489154053442292, 35.349088700930871 ] } },
{ "type": "Feature", "properties": { "osm_id": "879135261", "name": null, "highway": null, "waterway": null, "aerialway": null, "barrier": "hedge", "man_made": null, "z_order": 0, "other_tags": null }, "geometry": { "type": "Point", "coordinates": [ 139.48908849999998, 35.34906425 ] } }
]
}
