{
"type": "FeatureCollection",
"name": "map-points",
"crs": { "type": "name", "properties": { "name": "urn:ogc:def:crs:OGC:1.3:CRS84" } },
"features": [
{ "type": "Feature", "properties": { "osm_id": "444313641", "name": null, "barrier": null, "highway": null, "ref": null, "address": null, "is_in": null, "place": null, "man_made": null, "other_tags": "\"description\"=>\"高射砲座跡\",\"historic\"=>\"ruins\"", "area": null, "centroid_x": 139.6952134, "centroid_y": 35.2867833 }, "geometry": { "type": "Point", "coordinates": [ 139.6952134, 35.2867833 ] } },
{ "type": "Feature", "properties": { "osm_id": "444313651", "name": null, "barrier": null, "highway": null, "ref": null, "address": null, "is_in": null, "place": null, "man_made": null, "other_tags": "\"description\"=>\"高射砲座跡\",\"historic\"=>\"ruins\"", "area": null, "centroid_x": 139.6953335, "centroid_y": 35.2869304 }, "geometry": { "type": "Point", "coordinates": [ 139.6953335, 35.2869304 ] } },
{ "type": "Feature", "properties": { "osm_id": "444313737", "name": null, "barrier": null, "highway": null, "ref": null, "address": null, "is_in": null, "place": null, "man_made": null, "other_tags": "\"description\"=>\"高射砲座跡\",\"historic\"=>\"ruins\"", "area": null, "centroid_x": 139.6951189, "centroid_y": 35.2872457 }, "geometry": { "type": "Point", "coordinates": [ 139.695118900000011, 35.2872457 ] } },
{ "type": "Feature", "properties": { "osm_id": "444313871", "name": null, "barrier": null, "highway": null, "ref": null, "address": null, "is_in": null, "place": null, "man_made": null, "other_tags": "\"description\"=>\"高射砲座跡\",\"historic\"=>\"ruins\"", "area": null, "centroid_x": 139.6949765, "centroid_y": 35.2874872 }, "geometry": { "type": "Point", "coordinates": [ 139.6949765, 35.2874872 ] } },
{ "type": "Feature", "properties": { "osm_id": "444315773", "name": null, "barrier": null, "highway": null, "ref": null, "address": null, "is_in": null, "place": null, "man_made": null, "other_tags": "\"description\"=>\"展望台跡\",\"historic\"=>\"ruins\"", "area": null, "centroid_x": 139.6944295, "centroid_y": 35.2865479 }, "geometry": { "type": "Point", "coordinates": [ 139.694429500000012, 35.2865479 ] } },
{ "type": "Feature", "properties": { "osm_id": "444320430", "name": null, "barrier": null, "highway": null, "ref": null, "address": null, "is_in": null, "place": null, "man_made": null, "other_tags": "\"generator:source\"=>\"oil\",\"power\"=>\"generator\"", "area": null, "centroid_x": 139.6940155, "centroid_y": 35.2846968 }, "geometry": { "type": "Point", "coordinates": [ 139.6940155, 35.2846968 ] } },
{ "type": "Feature", "properties": { "osm_id": "444325703", "name": null, "barrier": null, "highway": null, "ref": null, "address": null, "is_in": null, "place": null, "man_made": "survey_point", "other_tags": "\"description\"=>\"三角点\"", "area": null, "centroid_x": 139.6942954, "centroid_y": 35.284515 }, "geometry": { "type": "Point", "coordinates": [ 139.694295399999987, 35.284515 ] } },
{ "type": "Feature", "properties": { "osm_id": "833617813", "name": null, "barrier": null, "highway": null, "ref": null, "address": null, "is_in": null, "place": null, "man_made": null, "other_tags": "\"amenity\"=>\"toilets\"", "area": null, "centroid_x": 139.6936608, "centroid_y": 35.284636 }, "geometry": { "type": "Point", "coordinates": [ 139.6936608, 35.284636 ] } },
{ "type": "Feature", "properties": { "osm_id": "4716000959", "name": null, "barrier": null, "highway": null, "ref": null, "address": null, "is_in": null, "place": null, "man_made": null, "other_tags": "\"tourism\"=>\"viewpoint\"", "area": null, "centroid_x": 139.6960873, "centroid_y": 35.2867865 }, "geometry": { "type": "Point", "coordinates": [ 139.696087299999988, 35.2867865 ] } },
{ "type": "Feature", "properties": { "osm_id": "4958114755", "name": "台場跡", "barrier": null, "highway": null, "ref": null, "address": null, "is_in": null, "place": null, "man_made": null, "other_tags": "\"historic\"=>\"ruins\"", "area": null, "centroid_x": 139.6960616, "centroid_y": 35.2867834 }, "geometry": { "type": "Point", "coordinates": [ 139.6960616, 35.2867834 ] } },
{ "type": "Feature", "properties": { "osm_id": "4958114760", "name": "日蓮洞穴", "barrier": null, "highway": null, "ref": null, "address": null, "is_in": null, "place": null, "man_made": null, "other_tags": "\"historic\"=>\"ruins\"", "area": null, "centroid_x": 139.6949843, "centroid_y": 35.2877122 }, "geometry": { "type": "Point", "coordinates": [ 139.694984299999987, 35.2877122 ] } },
{ "type": "Feature", "properties": { "osm_id": "4958114762", "name": null, "barrier": null, "highway": null, "ref": null, "address": null, "is_in": null, "place": null, "man_made": null, "other_tags": "\"shop\"=>\"convenience\"", "area": null, "centroid_x": 139.6937451, "centroid_y": 35.2846344 }, "geometry": { "type": "Point", "coordinates": [ 139.6937451, 35.2846344 ] } },
{ "type": "Feature", "properties": { "osm_id": "4958114763", "name": null, "barrier": null, "highway": null, "ref": null, "address": null, "is_in": null, "place": null, "man_made": null, "other_tags": "\"amenity\"=>\"restaurant\"", "area": null, "centroid_x": 139.6933991, "centroid_y": 35.2846744 }, "geometry": { "type": "Point", "coordinates": [ 139.6933991, 35.2846744 ] } },
{ "type": "Feature", "properties": { "osm_id": "5919405685", "name": null, "barrier": null, "highway": null, "ref": null, "address": null, "is_in": null, "place": null, "man_made": null, "other_tags": "\"information\"=>\"office\",\"tourism\"=>\"information\"", "area": null, "centroid_x": 139.6935929, "centroid_y": 35.2847247 }, "geometry": { "type": "Point", "coordinates": [ 139.6935929, 35.2847247 ] } },
{ "type": "Feature", "properties": { "osm_id": "5919405686", "name": null, "barrier": null, "highway": null, "ref": null, "address": null, "is_in": null, "place": null, "man_made": null, "other_tags": "\"leisure\"=>\"picnic_table\"", "area": null, "centroid_x": 139.6934775, "centroid_y": 35.2846464 }, "geometry": { "type": "Point", "coordinates": [ 139.6934775, 35.2846464 ] } },
{ "type": "Feature", "properties": { "osm_id": "5919405687", "name": null, "barrier": null, "highway": null, "ref": null, "address": null, "is_in": null, "place": null, "man_made": null, "other_tags": "\"leisure\"=>\"picnic_table\"", "area": null, "centroid_x": 139.6936445, "centroid_y": 35.2845791 }, "geometry": { "type": "Point", "coordinates": [ 139.6936445, 35.2845791 ] } },
{ "type": "Feature", "properties": { "osm_id": "5919405688", "name": "猿島公園　エコミュージアム猿島", "barrier": null, "highway": null, "ref": null, "address": null, "is_in": null, "place": null, "man_made": null, "other_tags": "\"information\"=>\"map\",\"tourism\"=>\"information\"", "area": null, "centroid_x": 139.693678, "centroid_y": 35.2845441 }, "geometry": { "type": "Point", "coordinates": [ 139.693678, 35.2845441 ] } },
{ "type": "Feature", "properties": { "osm_id": "5919405689", "name": "猿島の自然と歴史資源", "barrier": null, "highway": null, "ref": null, "address": null, "is_in": null, "place": null, "man_made": null, "other_tags": "\"information\"=>\"map\",\"tourism\"=>\"information\"", "area": null, "centroid_x": 139.6940582, "centroid_y": 35.2845298 }, "geometry": { "type": "Point", "coordinates": [ 139.6940582, 35.2845298 ] } },
{ "type": "Feature", "properties": { "osm_id": "5919405690", "name": "第一砲台", "barrier": null, "highway": null, "ref": null, "address": null, "is_in": null, "place": null, "man_made": null, "other_tags": "\"information\"=>\"board\",\"tourism\"=>\"information\"", "area": null, "centroid_x": 139.6948569, "centroid_y": 35.2867653 }, "geometry": { "type": "Point", "coordinates": [ 139.6948569, 35.2867653 ] } },
{ "type": "Feature", "properties": { "osm_id": "5919405691", "name": "砲台地下施設", "barrier": null, "highway": null, "ref": null, "address": null, "is_in": null, "place": null, "man_made": null, "other_tags": "\"information\"=>\"board\",\"tourism\"=>\"information\"", "area": null, "centroid_x": 139.6944639, "centroid_y": 35.2866465 }, "geometry": { "type": "Point", "coordinates": [ 139.694463899999988, 35.2866465 ] } },
{ "type": "Feature", "properties": { "osm_id": "5919405692", "name": "フランス積れんが建造物", "barrier": null, "highway": null, "ref": null, "address": null, "is_in": null, "place": null, "man_made": null, "other_tags": "\"information\"=>\"board\",\"tourism\"=>\"information\"", "area": null, "centroid_x": 139.6941843, "centroid_y": 35.2862847 }, "geometry": { "type": "Point", "coordinates": [ 139.694184299999989, 35.2862847 ] } },
{ "type": "Feature", "properties": { "osm_id": "5919405693", "name": "弾薬庫", "barrier": null, "highway": null, "ref": null, "address": null, "is_in": null, "place": null, "man_made": null, "other_tags": "\"information\"=>\"board\",\"tourism\"=>\"information\"", "area": null, "centroid_x": 139.6938443, "centroid_y": 35.2858402 }, "geometry": { "type": "Point", "coordinates": [ 139.6938443, 35.2858402 ] } },
{ "type": "Feature", "properties": { "osm_id": "5919405694", "name": "猿島要塞", "barrier": null, "highway": null, "ref": null, "address": null, "is_in": null, "place": null, "man_made": null, "other_tags": "\"information\"=>\"board\",\"tourism\"=>\"information\"", "area": null, "centroid_x": 139.6936847, "centroid_y": 35.2851757 }, "geometry": { "type": "Point", "coordinates": [ 139.6936847, 35.2851757 ] } },
{ "type": "Feature", "properties": { "osm_id": "5919405695", "name": null, "barrier": null, "highway": null, "ref": null, "address": null, "is_in": null, "place": null, "man_made": null, "other_tags": "\"information\"=>\"guidepost\",\"tourism\"=>\"information\"", "area": null, "centroid_x": 139.694128, "centroid_y": 35.2846546 }, "geometry": { "type": "Point", "coordinates": [ 139.694128, 35.2846546 ] } },
{ "type": "Feature", "properties": { "osm_id": "5919405696", "name": null, "barrier": null, "highway": null, "ref": "5", "address": null, "is_in": null, "place": null, "man_made": null, "other_tags": "\"emergency\"=>\"access_point\",\"information\"=>\"board\"", "area": null, "centroid_x": 139.6949407, "centroid_y": 35.2875206 }, "geometry": { "type": "Point", "coordinates": [ 139.694940699999989, 35.2875206 ] } },
{ "type": "Feature", "properties": { "osm_id": "5919405697", "name": null, "barrier": null, "highway": null, "ref": "8", "address": null, "is_in": null, "place": null, "man_made": null, "other_tags": "\"emergency\"=>\"access_point\",\"information\"=>\"board\"", "area": null, "centroid_x": 139.6942151, "centroid_y": 35.2845398 }, "geometry": { "type": "Point", "coordinates": [ 139.6942151, 35.2845398 ] } },
{ "type": "Feature", "properties": { "osm_id": "5919405698", "name": null, "barrier": null, "highway": null, "ref": null, "address": null, "is_in": null, "place": null, "man_made": null, "other_tags": "\"leisure\"=>\"picnic_table\"", "area": null, "centroid_x": 139.6942813, "centroid_y": 35.2845269 }, "geometry": { "type": "Point", "coordinates": [ 139.6942813, 35.2845269 ] } },
{ "type": "Feature", "properties": { "osm_id": "5919405699", "name": null, "barrier": null, "highway": null, "ref": null, "address": null, "is_in": null, "place": null, "man_made": null, "other_tags": "\"information\"=>\"map\",\"map_type\"=>\"toposcope\",\"tourism\"=>\"information\"", "area": null, "centroid_x": 139.6943392, "centroid_y": 35.2844444 }, "geometry": { "type": "Point", "coordinates": [ 139.6943392, 35.2844444 ] } },
{ "type": "Feature", "properties": { "osm_id": "5919405700", "name": null, "barrier": null, "highway": null, "ref": null, "address": null, "is_in": null, "place": null, "man_made": null, "other_tags": "\"historic\"=>\"ruins\"", "area": null, "centroid_x": 139.6940877, "centroid_y": 35.2859721 }, "geometry": { "type": "Point", "coordinates": [ 139.694087700000011, 35.2859721 ] } },
{ "type": "Feature", "properties": { "osm_id": "5919405701", "name": null, "barrier": null, "highway": null, "ref": null, "address": null, "is_in": null, "place": null, "man_made": null, "other_tags": "\"leisure\"=>\"picnic_table\"", "area": null, "centroid_x": 139.694256, "centroid_y": 35.2864779 }, "geometry": { "type": "Point", "coordinates": [ 139.694256, 35.2864779 ] } },
{ "type": "Feature", "properties": { "osm_id": "5919405702", "name": "頂上広場のパノラマ", "barrier": null, "highway": null, "ref": null, "address": null, "is_in": null, "place": null, "man_made": null, "other_tags": "\"information\"=>\"map\",\"map_type\"=>\"toposcope\",\"tourism\"=>\"information\"", "area": null, "centroid_x": 139.6941957, "centroid_y": 35.2864752 }, "geometry": { "type": "Point", "coordinates": [ 139.6941957, 35.2864752 ] } },
{ "type": "Feature", "properties": { "osm_id": "5919405703", "name": "案内図", "barrier": null, "highway": null, "ref": "7", "address": null, "is_in": null, "place": null, "man_made": null, "other_tags": "\"emergency\"=>\"access_point\",\"information\"=>\"map\",\"map_size\"=>\"site\",\"tourism\"=>\"information\"", "area": null, "centroid_x": 139.6943346, "centroid_y": 35.286408 }, "geometry": { "type": "Point", "coordinates": [ 139.6943346, 35.286408 ] } },
{ "type": "Feature", "properties": { "osm_id": "5919405704", "name": "台場跡", "barrier": null, "highway": null, "ref": null, "address": null, "is_in": null, "place": null, "man_made": null, "other_tags": "\"information\"=>\"map\",\"map_size\"=>\"site\",\"tourism\"=>\"information\"", "area": null, "centroid_x": 139.6960173, "centroid_y": 35.286773 }, "geometry": { "type": "Point", "coordinates": [ 139.6960173, 35.286773 ] } },
{ "type": "Feature", "properties": { "osm_id": "5919405705", "name": null, "barrier": null, "highway": null, "ref": null, "address": null, "is_in": null, "place": null, "man_made": null, "other_tags": "\"leisure\"=>\"picnic_table\"", "area": null, "centroid_x": 139.6960461, "centroid_y": 35.2868293 }, "geometry": { "type": "Point", "coordinates": [ 139.6960461, 35.2868293 ] } },
{ "type": "Feature", "properties": { "osm_id": "5919405706", "name": "卯の崎広場のパノラマ", "barrier": null, "highway": null, "ref": null, "address": null, "is_in": null, "place": null, "man_made": null, "other_tags": "\"information\"=>\"map\",\"map_type\"=>\"toposcope\",\"tourism\"=>\"information\"", "area": null, "centroid_x": 139.6961067, "centroid_y": 35.286897 }, "geometry": { "type": "Point", "coordinates": [ 139.6961067, 35.286897 ] } },
{ "type": "Feature", "properties": { "osm_id": "5919405707", "name": null, "barrier": null, "highway": null, "ref": null, "address": null, "is_in": null, "place": null, "man_made": null, "other_tags": "\"information\"=>\"guidepost\",\"tourism\"=>\"information\"", "area": null, "centroid_x": 139.6951693, "centroid_y": 35.2870753 }, "geometry": { "type": "Point", "coordinates": [ 139.6951693, 35.2870753 ] } },
{ "type": "Feature", "properties": { "osm_id": "5919405708", "name": "砲台跡", "barrier": null, "highway": null, "ref": null, "address": null, "is_in": null, "place": null, "man_made": null, "other_tags": "\"information\"=>\"board\",\"tourism\"=>\"information\"", "area": null, "centroid_x": 139.6949655, "centroid_y": 35.2874582 }, "geometry": { "type": "Point", "coordinates": [ 139.6949655, 35.2874582 ] } },
{ "type": "Feature", "properties": { "osm_id": "5919405709", "name": null, "barrier": null, "highway": null, "ref": null, "address": null, "is_in": null, "place": null, "man_made": null, "other_tags": "\"amenity\"=>\"bench\"", "area": null, "centroid_x": 139.6949249, "centroid_y": 35.287499 }, "geometry": { "type": "Point", "coordinates": [ 139.6949249, 35.287499 ] } },
{ "type": "Feature", "properties": { "osm_id": "5919405710", "name": null, "barrier": null, "highway": null, "ref": null, "address": null, "is_in": null, "place": null, "man_made": null, "other_tags": "\"information\"=>\"guidepost\",\"tourism\"=>\"information\"", "area": null, "centroid_x": 139.6950366, "centroid_y": 35.2875015 }, "geometry": { "type": "Point", "coordinates": [ 139.6950366, 35.2875015 ] } },
{ "type": "Feature", "properties": { "osm_id": "5919405711", "name": "日蓮洞窟に残された貝塚", "barrier": null, "highway": null, "ref": null, "address": null, "is_in": null, "place": null, "man_made": null, "other_tags": "\"information\"=>\"board\",\"tourism\"=>\"information\"", "area": null, "centroid_x": 139.6949908, "centroid_y": 35.2877089 }, "geometry": { "type": "Point", "coordinates": [ 139.6949908, 35.2877089 ] } },
{ "type": "Feature", "properties": { "osm_id": "8837224188", "name": "猿島", "barrier": null, "highway": null, "ref": null, "address": null, "is_in": null, "place": "neighbourhood", "man_made": null, "other_tags": "\"name:en\"=>\"Sarushima\",\"name:fr\"=>\"Île des Singes\",\"name:ja-Hira\"=>\"さるしま\",\"name:ja-Latn\"=>\"Saru-shima\",\"postal_code\"=>\"238-0019\"", "area": null, "centroid_x": 139.6940151, "centroid_y": 35.2860861 }, "geometry": { "type": "Point", "coordinates": [ 139.6940151, 35.2860861 ] } },
{ "type": "Feature", "properties": { "osm_id": "11171699179", "name": null, "barrier": null, "highway": null, "ref": null, "address": null, "is_in": null, "place": null, "man_made": null, "other_tags": "\"amenity\"=>\"toilets\"", "area": null, "centroid_x": 139.6932971, "centroid_y": 35.2850097 }, "geometry": { "type": "Point", "coordinates": [ 139.6932971, 35.2850097 ] } }
]
}
